{
  "segment_id": "table_p864_idx254",
  "table_id": null,
  "table_number": null,
  "caption": "relationships. In all cases, you can see that a positive alpha is necessary to out-",
  "row_headers": [
    [
      "Relation to alpha"
    ],
    [
      "Improvement compared to market index"
    ]
  ],
  "col_headers": [
    "",
    "",
    "Treynor (T )\np",
    "",
    "Sharpe* (S )\np",
    "",
    "Information Ratio"
  ],
  "cells": [
    [
      "",
      "",
      "Treynor (T )\np",
      "",
      "Sharpe* (S )\np",
      "",
      "Information Ratio"
    ],
    [
      "Relation to alpha",
      "",
      "_ E _ (r _p β _ ) p _ − _ r _f = _α β _ p p + T M",
      "",
      "_ E _ (r _p σ _ ) p _ − _ r _f = _ σ α_p p + ρ S M",
      "",
      "__α_p _\nσ(e )\np"
    ],
    [
      "Improvement compared to market index",
      "",
      "T p − T M = _α β _ p p",
      "",
      "S p − S M = _ σ α_p p − (1 − ρ)S M",
      "",
      "__α_p _\nσ(e )\np"
    ]
  ],
  "cell_meta": [
    {
      "row_index": 0,
      "col_index": 0,
      "bbox": {
        "x0": 0,
        "y0": 0,
        "x1": 0,
        "y1": 0
      },
      "cell_type": "blank",
      "raw_value": "",
      "normalized_value": "",
      "rowspan": 1,
      "colspan": 1,
      "formula_text": null,
      "units": null
    },
    {
      "row_index": 0,
      "col_index": 1,
      "bbox": {
        "x0": 0,
        "y0": 0,
        "x1": 0,
        "y1": 0
      },
      "cell_type": "blank",
      "raw_value": "",
      "normalized_value": "",
      "rowspan": 1,
      "colspan": 1,
      "formula_text": null,
      "units": null
    },
    {
      "row_index": 0,
      "col_index": 2,
      "bbox": {
        "x0": 0,
        "y0": 0,
        "x1": 0,
        "y1": 0
      },
      "cell_type": "text",
      "raw_value": "Treynor (T )\np",
      "normalized_value": "Treynor (T )\np",
      "rowspan": 1,
      "colspan": 1,
      "formula_text": null,
      "units": null
    },
    {
      "row_index": 0,
      "col_index": 3,
      "bbox": {
        "x0": 0,
        "y0": 0,
        "x1": 0,
        "y1": 0
      },
      "cell_type": "blank",
      "raw_value": "",
      "normalized_value": "",
      "rowspan": 1,
      "colspan": 1,
      "formula_text": null,
      "units": null
    },
    {
      "row_index": 0,
      "col_index": 4,
      "bbox": {
        "x0": 0,
        "y0": 0,
        "x1": 0,
        "y1": 0
      },
      "cell_type": "text",
      "raw_value": "Sharpe* (S )\np",
      "normalized_value": "Sharpe* (S )\np",
      "rowspan": 1,
      "colspan": 1,
      "formula_text": null,
      "units": null
    },
    {
      "row_index": 0,
      "col_index": 5,
      "bbox": {
        "x0": 0,
        "y0": 0,
        "x1": 0,
        "y1": 0
      },
      "cell_type": "blank",
      "raw_value": "",
      "normalized_value": "",
      "rowspan": 1,
      "colspan": 1,
      "formula_text": null,
      "units": null
    },
    {
      "row_index": 0,
      "col_index": 6,
      "bbox": {
        "x0": 0,
        "y0": 0,
        "x1": 0,
        "y1": 0
      },
      "cell_type": "text",
      "raw_value": "Information Ratio",
      "normalized_value": "Information Ratio",
      "rowspan": 1,
      "colspan": 1,
      "formula_text": null,
      "units": null
    },
    {
      "row_index": 1,
      "col_index": 0,
      "bbox": {
        "x0": 0,
        "y0": 0,
        "x1": 0,
        "y1": 0
      },
      "cell_type": "text",
      "raw_value": "Relation to alpha",
      "normalized_value": "Relation to alpha",
      "rowspan": 1,
      "colspan": 1,
      "formula_text": null,
      "units": null
    },
    {
      "row_index": 1,
      "col_index": 1,
      "bbox": {
        "x0": 0,
        "y0": 0,
        "x1": 0,
        "y1": 0
      },
      "cell_type": "blank",
      "raw_value": "",
      "normalized_value": "",
      "rowspan": 1,
      "colspan": 1,
      "formula_text": null,
      "units": null
    },
    {
      "row_index": 1,
      "col_index": 2,
      "bbox": {
        "x0": 0,
        "y0": 0,
        "x1": 0,
        "y1": 0
      },
      "cell_type": "formula",
      "raw_value": "_ E _ (r _p β _ ) p _ − _ r _f = _α β _ p p + T M",
      "normalized_value": "_ E _ (r _p β _ ) p _ − _ r _f = _α β _ p p + T M",
      "rowspan": 1,
      "colspan": 1,
      "formula_text": null,
      "units": null
    },
    {
      "row_index": 1,
      "col_index": 3,
      "bbox": {
        "x0": 0,
        "y0": 0,
        "x1": 0,
        "y1": 0
      },
      "cell_type": "blank",
      "raw_value": "",
      "normalized_value": "",
      "rowspan": 1,
      "colspan": 1,
      "formula_text": null,
      "units": null
    },
    {
      "row_index": 1,
      "col_index": 4,
      "bbox": {
        "x0": 0,
        "y0": 0,
        "x1": 0,
        "y1": 0
      },
      "cell_type": "formula",
      "raw_value": "_ E _ (r _p σ _ ) p _ − _ r _f = _ σ α_p p + ρ S M",
      "normalized_value": "_ E _ (r _p σ _ ) p _ − _ r _f = _ σ α_p p + ρ S M",
      "rowspan": 1,
      "colspan": 1,
      "formula_text": null,
      "units": null
    },
    {
      "row_index": 1,
      "col_index": 5,
      "bbox": {
        "x0": 0,
        "y0": 0,
        "x1": 0,
        "y1": 0
      },
      "cell_type": "blank",
      "raw_value": "",
      "normalized_value": "",
      "rowspan": 1,
      "colspan": 1,
      "formula_text": null,
      "units": null
    },
    {
      "row_index": 1,
      "col_index": 6,
      "bbox": {
        "x0": 0,
        "y0": 0,
        "x1": 0,
        "y1": 0
      },
      "cell_type": "text",
      "raw_value": "__α_p _\nσ(e )\np",
      "normalized_value": "__α_p _\nσ(e )\np",
      "rowspan": 1,
      "colspan": 1,
      "formula_text": null,
      "units": null
    },
    {
      "row_index": 2,
      "col_index": 0,
      "bbox": {
        "x0": 0,
        "y0": 0,
        "x1": 0,
        "y1": 0
      },
      "cell_type": "text",
      "raw_value": "Improvement compared to market index",
      "normalized_value": "Improvement compared to market index",
      "rowspan": 1,
      "colspan": 1,
      "formula_text": null,
      "units": null
    },
    {
      "row_index": 2,
      "col_index": 1,
      "bbox": {
        "x0": 0,
        "y0": 0,
        "x1": 0,
        "y1": 0
      },
      "cell_type": "blank",
      "raw_value": "",
      "normalized_value": "",
      "rowspan": 1,
      "colspan": 1,
      "formula_text": null,
      "units": null
    },
    {
      "row_index": 2,
      "col_index": 2,
      "bbox": {
        "x0": 0,
        "y0": 0,
        "x1": 0,
        "y1": 0
      },
      "cell_type": "formula",
      "raw_value": "T p − T M = _α β _ p p",
      "normalized_value": "T p − T M = _α β _ p p",
      "rowspan": 1,
      "colspan": 1,
      "formula_text": null,
      "units": null
    },
    {
      "row_index": 2,
      "col_index": 3,
      "bbox": {
        "x0": 0,
        "y0": 0,
        "x1": 0,
        "y1": 0
      },
      "cell_type": "blank",
      "raw_value": "",
      "normalized_value": "",
      "rowspan": 1,
      "colspan": 1,
      "formula_text": null,
      "units": null
    },
    {
      "row_index": 2,
      "col_index": 4,
      "bbox": {
        "x0": 0,
        "y0": 0,
        "x1": 0,
        "y1": 0
      },
      "cell_type": "formula",
      "raw_value": "S p − S M = _ σ α_p p − (1 − ρ)S M",
      "normalized_value": "S p − S M = _ σ α_p p − (1 − ρ)S M",
      "rowspan": 1,
      "colspan": 1,
      "formula_text": null,
      "units": null
    },
    {
      "row_index": 2,
      "col_index": 5,
      "bbox": {
        "x0": 0,
        "y0": 0,
        "x1": 0,
        "y1": 0
      },
      "cell_type": "blank",
      "raw_value": "",
      "normalized_value": "",
      "rowspan": 1,
      "colspan": 1,
      "formula_text": null,
      "units": null
    },
    {
      "row_index": 2,
      "col_index": 6,
      "bbox": {
        "x0": 0,
        "y0": 0,
        "x1": 0,
        "y1": 0
      },
      "cell_type": "text",
      "raw_value": "__α_p _\nσ(e )\np",
      "normalized_value": "__α_p _\nσ(e )\np",
      "rowspan": 1,
      "colspan": 1,
      "formula_text": null,
      "units": null
    }
  ],
  "footnotes": [],
  "units": [],
  "formula_cells": [
    {
      "cell_address": "C2",
      "formula_text": "_ E _ (r _p β _ ) p _ − _ r _f = _α β _ p p + T M",
      "bbox": {
        "x0": 0,
        "y0": 0,
        "x1": 0,
        "y1": 0
      },
      "source_anchor": {
        "page_number": 864,
        "bbox": {
          "x0": 108.2500534,
          "y0": 526.2799001999999,
          "x1": 512.7511485,
          "y1": 600.7898517
        },
        "extractor": "pdfplumber",
        "confidence": 0.9,
        "metadata": {}
      },
      "confidence": 0.9
    },
    {
      "cell_address": "E2",
      "formula_text": "_ E _ (r _p σ _ ) p _ − _ r _f = _ σ α_p p + ρ S M",
      "bbox": {
        "x0": 0,
        "y0": 0,
        "x1": 0,
        "y1": 0
      },
      "source_anchor": {
        "page_number": 864,
        "bbox": {
          "x0": 108.2500534,
          "y0": 526.2799001999999,
          "x1": 512.7511485,
          "y1": 600.7898517
        },
        "extractor": "pdfplumber",
        "confidence": 0.9,
        "metadata": {}
      },
      "confidence": 0.9
    },
    {
      "cell_address": "C3",
      "formula_text": "T p − T M = _α β _ p p",
      "bbox": {
        "x0": 0,
        "y0": 0,
        "x1": 0,
        "y1": 0
      },
      "source_anchor": {
        "page_number": 864,
        "bbox": {
          "x0": 108.2500534,
          "y0": 526.2799001999999,
          "x1": 512.7511485,
          "y1": 600.7898517
        },
        "extractor": "pdfplumber",
        "confidence": 0.9,
        "metadata": {}
      },
      "confidence": 0.9
    },
    {
      "cell_address": "E3",
      "formula_text": "S p − S M = _ σ α_p p − (1 − ρ)S M",
      "bbox": {
        "x0": 0,
        "y0": 0,
        "x1": 0,
        "y1": 0
      },
      "source_anchor": {
        "page_number": 864,
        "bbox": {
          "x0": 108.2500534,
          "y0": 526.2799001999999,
          "x1": 512.7511485,
          "y1": 600.7898517
        },
        "extractor": "pdfplumber",
        "confidence": 0.9,
        "metadata": {}
      },
      "confidence": 0.9
    }
  ],
  "derived_columns": [],
  "variable_candidates": {},
  "description": "relationships. In all cases, you can see that a positive alpha is necessary to out- This table contains 3 rows and 7 columns.",
  "table_summary": "relationships. In all cases, you can see that a positive alpha is necessary to out- This table contains 3 rows and 7 columns.",
  "table_schema_hint": null,
  "linked_concept_ids": [
    "financial_analysis"
  ],
  "links": [
    {
      "link_type": "TABLE_OF",
      "target_id": "financial_analysis",
      "source_anchor": {
        "page_number": 864,
        "bbox": {
          "x0": 108.2500534,
          "y0": 526.2799001999999,
          "x1": 512.7511485,
          "y1": 600.7898517
        },
        "extractor": "pdfplumber",
        "confidence": 0.9,
        "metadata": {}
      },
      "evidence": "Semantic similarity: 0.37 + Keywords: ratio",
      "confidence": 0.5656190931797027
    }
  ],
  "source_anchor": {
    "page_number": 864,
    "bbox": {
      "x0": 108.2500534,
      "y0": 526.2799001999999,
      "x1": 512.7511485,
      "y1": 600.7898517
    },
    "extractor": "pdfplumber",
    "confidence": 0.9,
    "metadata": {}
  },
  "confidence": 1.0,
  "heading_path": null,
  "page_span": [
    864,
    864
  ]
}