{
  "segment_id": "table_p340_idx0",
  "table_id": null,
  "table_number": null,
  "caption": "",
  "row_headers": [
    [
      "Portfolio"
    ],
    [
      "R"
    ],
    [
      "S&P"
    ]
  ],
  "col_headers": [
    "",
    "",
    "Average",
    "Annual",
    "",
    "",
    ""
  ],
  "cells": [
    [
      "",
      "",
      "Average",
      "Annual",
      "",
      "",
      ""
    ],
    [
      "Portfolio",
      "",
      "Rate",
      "of Return",
      "Standard",
      "Deviation",
      "Beta"
    ],
    [
      "R",
      "",
      "",
      "11%",
      "",
      "10%",
      "0.5"
    ],
    [
      "S&P",
      "500",
      "",
      "14%",
      "",
      "12%",
      "1.0"
    ]
  ],
  "cell_meta": [
    {
      "row_index": 0,
      "col_index": 0,
      "bbox": {
        "x0": 0,
        "y0": 0,
        "x1": 0,
        "y1": 0
      },
      "cell_type": "blank",
      "raw_value": "",
      "normalized_value": "",
      "rowspan": 1,
      "colspan": 1,
      "formula_text": null,
      "units": null
    },
    {
      "row_index": 0,
      "col_index": 1,
      "bbox": {
        "x0": 0,
        "y0": 0,
        "x1": 0,
        "y1": 0
      },
      "cell_type": "blank",
      "raw_value": "",
      "normalized_value": "",
      "rowspan": 1,
      "colspan": 1,
      "formula_text": null,
      "units": null
    },
    {
      "row_index": 0,
      "col_index": 2,
      "bbox": {
        "x0": 155.0,
        "y0": 8.0,
        "x1": 235.0,
        "y1": 27.0
      },
      "cell_type": "text",
      "raw_value": "Average",
      "normalized_value": "Average",
      "rowspan": 1,
      "colspan": 1,
      "formula_text": null,
      "units": null
    },
    {
      "row_index": 0,
      "col_index": 3,
      "bbox": {
        "x0": 242.0,
        "y0": 8.0,
        "x1": 308.0,
        "y1": 23.0
      },
      "cell_type": "text",
      "raw_value": "Annual",
      "normalized_value": "Annual",
      "rowspan": 1,
      "colspan": 1,
      "formula_text": null,
      "units": null
    },
    {
      "row_index": 0,
      "col_index": 4,
      "bbox": {
        "x0": 0,
        "y0": 0,
        "x1": 0,
        "y1": 0
      },
      "cell_type": "blank",
      "raw_value": "",
      "normalized_value": "",
      "rowspan": 1,
      "colspan": 1,
      "formula_text": null,
      "units": null
    },
    {
      "row_index": 0,
      "col_index": 5,
      "bbox": {
        "x0": 0,
        "y0": 0,
        "x1": 0,
        "y1": 0
      },
      "cell_type": "blank",
      "raw_value": "",
      "normalized_value": "",
      "rowspan": 1,
      "colspan": 1,
      "formula_text": null,
      "units": null
    },
    {
      "row_index": 0,
      "col_index": 6,
      "bbox": {
        "x0": 0,
        "y0": 0,
        "x1": 0,
        "y1": 0
      },
      "cell_type": "blank",
      "raw_value": "",
      "normalized_value": "",
      "rowspan": 1,
      "colspan": 1,
      "formula_text": null,
      "units": null
    },
    {
      "row_index": 1,
      "col_index": 0,
      "bbox": {
        "x0": 10.0,
        "y0": 31.0,
        "x1": 92.0,
        "y1": 60.0
      },
      "cell_type": "text",
      "raw_value": "Portfolio",
      "normalized_value": "Portfolio",
      "rowspan": 1,
      "colspan": 1,
      "formula_text": null,
      "units": null
    },
    {
      "row_index": 1,
      "col_index": 1,
      "bbox": {
        "x0": 0,
        "y0": 0,
        "x1": 0,
        "y1": 0
      },
      "cell_type": "blank",
      "raw_value": "",
      "normalized_value": "",
      "rowspan": 1,
      "colspan": 1,
      "formula_text": null,
      "units": null
    },
    {
      "row_index": 1,
      "col_index": 2,
      "bbox": {
        "x0": 165.0,
        "y0": 35.0,
        "x1": 206.0,
        "y1": 50.0
      },
      "cell_type": "text",
      "raw_value": "Rate",
      "normalized_value": "Rate",
      "rowspan": 1,
      "colspan": 1,
      "formula_text": null,
      "units": null
    },
    {
      "row_index": 1,
      "col_index": 3,
      "bbox": {
        "x0": 213.0,
        "y0": 35.0,
        "x1": 299.0,
        "y1": 50.0
      },
      "cell_type": "text",
      "raw_value": "of Return",
      "normalized_value": "of Return",
      "rowspan": 1,
      "colspan": 1,
      "formula_text": null,
      "units": null
    },
    {
      "row_index": 1,
      "col_index": 4,
      "bbox": {
        "x0": 369.0,
        "y0": 35.0,
        "x1": 454.0,
        "y1": 50.0
      },
      "cell_type": "text",
      "raw_value": "Standard",
      "normalized_value": "Standard",
      "rowspan": 1,
      "colspan": 1,
      "formula_text": null,
      "units": null
    },
    {
      "row_index": 1,
      "col_index": 5,
      "bbox": {
        "x0": 463.0,
        "y0": 35.0,
        "x1": 552.0,
        "y1": 50.0
      },
      "cell_type": "text",
      "raw_value": "Deviation",
      "normalized_value": "Deviation",
      "rowspan": 1,
      "colspan": 1,
      "formula_text": null,
      "units": null
    },
    {
      "row_index": 1,
      "col_index": 6,
      "bbox": {
        "x0": 614.0,
        "y0": 35.0,
        "x1": 656.0,
        "y1": 50.0
      },
      "cell_type": "text",
      "raw_value": "Beta",
      "normalized_value": "Beta",
      "rowspan": 1,
      "colspan": 1,
      "formula_text": null,
      "units": null
    },
    {
      "row_index": 2,
      "col_index": 0,
      "bbox": {
        "x0": 11.0,
        "y0": 81.0,
        "x1": 23.0,
        "y1": 96.0
      },
      "cell_type": "text",
      "raw_value": "R",
      "normalized_value": "R",
      "rowspan": 1,
      "colspan": 1,
      "formula_text": null,
      "units": null
    },
    {
      "row_index": 2,
      "col_index": 1,
      "bbox": {
        "x0": 0,
        "y0": 0,
        "x1": 0,
        "y1": 0
      },
      "cell_type": "blank",
      "raw_value": "",
      "normalized_value": "",
      "rowspan": 1,
      "colspan": 1,
      "formula_text": null,
      "units": null
    },
    {
      "row_index": 2,
      "col_index": 2,
      "bbox": {
        "x0": 0,
        "y0": 0,
        "x1": 0,
        "y1": 0
      },
      "cell_type": "blank",
      "raw_value": "",
      "normalized_value": "",
      "rowspan": 1,
      "colspan": 1,
      "formula_text": null,
      "units": null
    },
    {
      "row_index": 2,
      "col_index": 3,
      "bbox": {
        "x0": 215.0,
        "y0": 81.0,
        "x1": 252.0,
        "y1": 96.0
      },
      "cell_type": "percent",
      "raw_value": "11%",
      "normalized_value": 0.11,
      "rowspan": 1,
      "colspan": 1,
      "formula_text": null,
      "units": null
    },
    {
      "row_index": 2,
      "col_index": 4,
      "bbox": {
        "x0": 0,
        "y0": 0,
        "x1": 0,
        "y1": 0
      },
      "cell_type": "blank",
      "raw_value": "",
      "normalized_value": "",
      "rowspan": 1,
      "colspan": 1,
      "formula_text": null,
      "units": null
    },
    {
      "row_index": 2,
      "col_index": 5,
      "bbox": {
        "x0": 444.0,
        "y0": 81.0,
        "x1": 481.0,
        "y1": 96.0
      },
      "cell_type": "percent",
      "raw_value": "10%",
      "normalized_value": 0.1,
      "rowspan": 1,
      "colspan": 1,
      "formula_text": null,
      "units": null
    },
    {
      "row_index": 2,
      "col_index": 6,
      "bbox": {
        "x0": 620.0,
        "y0": 81.0,
        "x1": 649.0,
        "y1": 96.0
      },
      "cell_type": "number",
      "raw_value": "0.5",
      "normalized_value": 0.5,
      "rowspan": 1,
      "colspan": 1,
      "formula_text": null,
      "units": null
    },
    {
      "row_index": 3,
      "col_index": 0,
      "bbox": {
        "x0": 11.0,
        "y0": 116.0,
        "x1": 49.0,
        "y1": 131.0
      },
      "cell_type": "text",
      "raw_value": "S&P",
      "normalized_value": "S&P",
      "rowspan": 1,
      "colspan": 1,
      "formula_text": null,
      "units": null
    },
    {
      "row_index": 3,
      "col_index": 1,
      "bbox": {
        "x0": 57.0,
        "y0": 116.0,
        "x1": 94.0,
        "y1": 131.0
      },
      "cell_type": "number",
      "raw_value": "500",
      "normalized_value": 500,
      "rowspan": 1,
      "colspan": 1,
      "formula_text": null,
      "units": null
    },
    {
      "row_index": 3,
      "col_index": 2,
      "bbox": {
        "x0": 0,
        "y0": 0,
        "x1": 0,
        "y1": 0
      },
      "cell_type": "blank",
      "raw_value": "",
      "normalized_value": "",
      "rowspan": 1,
      "colspan": 1,
      "formula_text": null,
      "units": null
    },
    {
      "row_index": 3,
      "col_index": 3,
      "bbox": {
        "x0": 215.0,
        "y0": 116.0,
        "x1": 252.0,
        "y1": 131.0
      },
      "cell_type": "percent",
      "raw_value": "14%",
      "normalized_value": 0.14,
      "rowspan": 1,
      "colspan": 1,
      "formula_text": null,
      "units": null
    },
    {
      "row_index": 3,
      "col_index": 4,
      "bbox": {
        "x0": 0,
        "y0": 0,
        "x1": 0,
        "y1": 0
      },
      "cell_type": "blank",
      "raw_value": "",
      "normalized_value": "",
      "rowspan": 1,
      "colspan": 1,
      "formula_text": null,
      "units": null
    },
    {
      "row_index": 3,
      "col_index": 5,
      "bbox": {
        "x0": 444.0,
        "y0": 116.0,
        "x1": 481.0,
        "y1": 131.0
      },
      "cell_type": "percent",
      "raw_value": "12%",
      "normalized_value": 0.12,
      "rowspan": 1,
      "colspan": 1,
      "formula_text": null,
      "units": null
    },
    {
      "row_index": 3,
      "col_index": 6,
      "bbox": {
        "x0": 623.0,
        "y0": 116.0,
        "x1": 649.0,
        "y1": 131.0
      },
      "cell_type": "number",
      "raw_value": "1.0",
      "normalized_value": 1.0,
      "rowspan": 1,
      "colspan": 1,
      "formula_text": null,
      "units": null
    }
  ],
  "footnotes": [],
  "units": [],
  "formula_cells": [],
  "derived_columns": [],
  "variable_candidates": {},
  "description": "",
  "table_summary": "",
  "table_schema_hint": null,
  "linked_concept_ids": [],
  "links": [],
  "source_anchor": {
    "page_number": 340,
    "bbox": {
      "x0": 10.0,
      "y0": 8.0,
      "x1": 656.0,
      "y1": 131.0
    },
    "extractor": "ocr_image",
    "confidence": 0.6,
    "metadata": {}
  },
  "confidence": 1.0,
  "heading_path": "Part III: Equilibrium in Capital Markets > SUMMARY",
  "page_span": [
    340,
    340
  ],
  "source_chunk_id": "chunk_02715",
  "page_start": 340,
  "page_end": 340
}