{
  "segment_id": "table_p85_idx12",
  "table_id": null,
  "table_number": null,
  "caption": "Introduction",
  "row_headers": [
    [
      "Sep-21"
    ],
    [
      "Dec-21"
    ],
    [
      "May-22"
    ],
    [
      "Dec-22"
    ],
    [
      "Jul-23"
    ]
  ],
  "col_headers": [
    "Maturity",
    "",
    "Last",
    "",
    "Change",
    "",
    "High",
    "",
    "Low"
  ],
  "cells": [
    [
      "Maturity",
      "",
      "Last",
      "",
      "Change",
      "",
      "High",
      "",
      "Low"
    ],
    [
      "Sep-21",
      "",
      "5.6400",
      "",
      "−0.0425",
      "",
      "5.7150",
      "",
      "5.6100"
    ],
    [
      "Dec-21",
      "",
      "5.5500",
      "",
      "−0.0375",
      "",
      "5.6150",
      "",
      "5.5100"
    ],
    [
      "May-22",
      "",
      "5.6725",
      "",
      "−0.0350",
      "",
      "5.7300",
      "",
      "5.6350"
    ],
    [
      "Dec-22",
      "",
      "4.9575",
      "",
      "0.0175",
      "",
      "4.9750",
      "",
      "4.9025"
    ],
    [
      "Jul-23",
      "",
      "5.0400",
      "",
      "−0.0300",
      "",
      "5.0825",
      "",
      "5.0400"
    ]
  ],
  "cell_meta": [
    {
      "row_index": 0,
      "col_index": 0,
      "bbox": {
        "x0": 0,
        "y0": 0,
        "x1": 0,
        "y1": 0
      },
      "cell_type": "text",
      "raw_value": "Maturity",
      "normalized_value": "Maturity",
      "rowspan": 1,
      "colspan": 1,
      "formula_text": null,
      "units": null
    },
    {
      "row_index": 0,
      "col_index": 1,
      "bbox": {
        "x0": 0,
        "y0": 0,
        "x1": 0,
        "y1": 0
      },
      "cell_type": "blank",
      "raw_value": "",
      "normalized_value": "",
      "rowspan": 1,
      "colspan": 1,
      "formula_text": null,
      "units": null
    },
    {
      "row_index": 0,
      "col_index": 2,
      "bbox": {
        "x0": 0,
        "y0": 0,
        "x1": 0,
        "y1": 0
      },
      "cell_type": "text",
      "raw_value": "Last",
      "normalized_value": "Last",
      "rowspan": 1,
      "colspan": 1,
      "formula_text": null,
      "units": null
    },
    {
      "row_index": 0,
      "col_index": 3,
      "bbox": {
        "x0": 0,
        "y0": 0,
        "x1": 0,
        "y1": 0
      },
      "cell_type": "blank",
      "raw_value": "",
      "normalized_value": "",
      "rowspan": 1,
      "colspan": 1,
      "formula_text": null,
      "units": null
    },
    {
      "row_index": 0,
      "col_index": 4,
      "bbox": {
        "x0": 0,
        "y0": 0,
        "x1": 0,
        "y1": 0
      },
      "cell_type": "text",
      "raw_value": "Change",
      "normalized_value": "Change",
      "rowspan": 1,
      "colspan": 1,
      "formula_text": null,
      "units": null
    },
    {
      "row_index": 0,
      "col_index": 5,
      "bbox": {
        "x0": 0,
        "y0": 0,
        "x1": 0,
        "y1": 0
      },
      "cell_type": "blank",
      "raw_value": "",
      "normalized_value": "",
      "rowspan": 1,
      "colspan": 1,
      "formula_text": null,
      "units": null
    },
    {
      "row_index": 0,
      "col_index": 6,
      "bbox": {
        "x0": 0,
        "y0": 0,
        "x1": 0,
        "y1": 0
      },
      "cell_type": "text",
      "raw_value": "High",
      "normalized_value": "High",
      "rowspan": 1,
      "colspan": 1,
      "formula_text": null,
      "units": null
    },
    {
      "row_index": 0,
      "col_index": 7,
      "bbox": {
        "x0": 0,
        "y0": 0,
        "x1": 0,
        "y1": 0
      },
      "cell_type": "blank",
      "raw_value": "",
      "normalized_value": "",
      "rowspan": 1,
      "colspan": 1,
      "formula_text": null,
      "units": null
    },
    {
      "row_index": 0,
      "col_index": 8,
      "bbox": {
        "x0": 0,
        "y0": 0,
        "x1": 0,
        "y1": 0
      },
      "cell_type": "text",
      "raw_value": "Low",
      "normalized_value": "Low",
      "rowspan": 1,
      "colspan": 1,
      "formula_text": null,
      "units": null
    },
    {
      "row_index": 1,
      "col_index": 0,
      "bbox": {
        "x0": 0,
        "y0": 0,
        "x1": 0,
        "y1": 0
      },
      "cell_type": "text",
      "raw_value": "Sep-21",
      "normalized_value": "Sep-21",
      "rowspan": 1,
      "colspan": 1,
      "formula_text": null,
      "units": null
    },
    {
      "row_index": 1,
      "col_index": 1,
      "bbox": {
        "x0": 0,
        "y0": 0,
        "x1": 0,
        "y1": 0
      },
      "cell_type": "blank",
      "raw_value": "",
      "normalized_value": "",
      "rowspan": 1,
      "colspan": 1,
      "formula_text": null,
      "units": null
    },
    {
      "row_index": 1,
      "col_index": 2,
      "bbox": {
        "x0": 0,
        "y0": 0,
        "x1": 0,
        "y1": 0
      },
      "cell_type": "number",
      "raw_value": "5.6400",
      "normalized_value": 5.64,
      "rowspan": 1,
      "colspan": 1,
      "formula_text": null,
      "units": null
    },
    {
      "row_index": 1,
      "col_index": 3,
      "bbox": {
        "x0": 0,
        "y0": 0,
        "x1": 0,
        "y1": 0
      },
      "cell_type": "blank",
      "raw_value": "",
      "normalized_value": "",
      "rowspan": 1,
      "colspan": 1,
      "formula_text": null,
      "units": null
    },
    {
      "row_index": 1,
      "col_index": 4,
      "bbox": {
        "x0": 0,
        "y0": 0,
        "x1": 0,
        "y1": 0
      },
      "cell_type": "text",
      "raw_value": "−0.0425",
      "normalized_value": "−0.0425",
      "rowspan": 1,
      "colspan": 1,
      "formula_text": null,
      "units": null
    },
    {
      "row_index": 1,
      "col_index": 5,
      "bbox": {
        "x0": 0,
        "y0": 0,
        "x1": 0,
        "y1": 0
      },
      "cell_type": "blank",
      "raw_value": "",
      "normalized_value": "",
      "rowspan": 1,
      "colspan": 1,
      "formula_text": null,
      "units": null
    },
    {
      "row_index": 1,
      "col_index": 6,
      "bbox": {
        "x0": 0,
        "y0": 0,
        "x1": 0,
        "y1": 0
      },
      "cell_type": "number",
      "raw_value": "5.7150",
      "normalized_value": 5.715,
      "rowspan": 1,
      "colspan": 1,
      "formula_text": null,
      "units": null
    },
    {
      "row_index": 1,
      "col_index": 7,
      "bbox": {
        "x0": 0,
        "y0": 0,
        "x1": 0,
        "y1": 0
      },
      "cell_type": "blank",
      "raw_value": "",
      "normalized_value": "",
      "rowspan": 1,
      "colspan": 1,
      "formula_text": null,
      "units": null
    },
    {
      "row_index": 1,
      "col_index": 8,
      "bbox": {
        "x0": 0,
        "y0": 0,
        "x1": 0,
        "y1": 0
      },
      "cell_type": "number",
      "raw_value": "5.6100",
      "normalized_value": 5.61,
      "rowspan": 1,
      "colspan": 1,
      "formula_text": null,
      "units": null
    },
    {
      "row_index": 2,
      "col_index": 0,
      "bbox": {
        "x0": 0,
        "y0": 0,
        "x1": 0,
        "y1": 0
      },
      "cell_type": "text",
      "raw_value": "Dec-21",
      "normalized_value": "Dec-21",
      "rowspan": 1,
      "colspan": 1,
      "formula_text": null,
      "units": null
    },
    {
      "row_index": 2,
      "col_index": 1,
      "bbox": {
        "x0": 0,
        "y0": 0,
        "x1": 0,
        "y1": 0
      },
      "cell_type": "blank",
      "raw_value": "",
      "normalized_value": "",
      "rowspan": 1,
      "colspan": 1,
      "formula_text": null,
      "units": null
    },
    {
      "row_index": 2,
      "col_index": 2,
      "bbox": {
        "x0": 0,
        "y0": 0,
        "x1": 0,
        "y1": 0
      },
      "cell_type": "number",
      "raw_value": "5.5500",
      "normalized_value": 5.55,
      "rowspan": 1,
      "colspan": 1,
      "formula_text": null,
      "units": null
    },
    {
      "row_index": 2,
      "col_index": 3,
      "bbox": {
        "x0": 0,
        "y0": 0,
        "x1": 0,
        "y1": 0
      },
      "cell_type": "blank",
      "raw_value": "",
      "normalized_value": "",
      "rowspan": 1,
      "colspan": 1,
      "formula_text": null,
      "units": null
    },
    {
      "row_index": 2,
      "col_index": 4,
      "bbox": {
        "x0": 0,
        "y0": 0,
        "x1": 0,
        "y1": 0
      },
      "cell_type": "text",
      "raw_value": "−0.0375",
      "normalized_value": "−0.0375",
      "rowspan": 1,
      "colspan": 1,
      "formula_text": null,
      "units": null
    },
    {
      "row_index": 2,
      "col_index": 5,
      "bbox": {
        "x0": 0,
        "y0": 0,
        "x1": 0,
        "y1": 0
      },
      "cell_type": "blank",
      "raw_value": "",
      "normalized_value": "",
      "rowspan": 1,
      "colspan": 1,
      "formula_text": null,
      "units": null
    },
    {
      "row_index": 2,
      "col_index": 6,
      "bbox": {
        "x0": 0,
        "y0": 0,
        "x1": 0,
        "y1": 0
      },
      "cell_type": "number",
      "raw_value": "5.6150",
      "normalized_value": 5.615,
      "rowspan": 1,
      "colspan": 1,
      "formula_text": null,
      "units": null
    },
    {
      "row_index": 2,
      "col_index": 7,
      "bbox": {
        "x0": 0,
        "y0": 0,
        "x1": 0,
        "y1": 0
      },
      "cell_type": "blank",
      "raw_value": "",
      "normalized_value": "",
      "rowspan": 1,
      "colspan": 1,
      "formula_text": null,
      "units": null
    },
    {
      "row_index": 2,
      "col_index": 8,
      "bbox": {
        "x0": 0,
        "y0": 0,
        "x1": 0,
        "y1": 0
      },
      "cell_type": "number",
      "raw_value": "5.5100",
      "normalized_value": 5.51,
      "rowspan": 1,
      "colspan": 1,
      "formula_text": null,
      "units": null
    },
    {
      "row_index": 3,
      "col_index": 0,
      "bbox": {
        "x0": 0,
        "y0": 0,
        "x1": 0,
        "y1": 0
      },
      "cell_type": "text",
      "raw_value": "May-22",
      "normalized_value": "May-22",
      "rowspan": 1,
      "colspan": 1,
      "formula_text": null,
      "units": null
    },
    {
      "row_index": 3,
      "col_index": 1,
      "bbox": {
        "x0": 0,
        "y0": 0,
        "x1": 0,
        "y1": 0
      },
      "cell_type": "blank",
      "raw_value": "",
      "normalized_value": "",
      "rowspan": 1,
      "colspan": 1,
      "formula_text": null,
      "units": null
    },
    {
      "row_index": 3,
      "col_index": 2,
      "bbox": {
        "x0": 0,
        "y0": 0,
        "x1": 0,
        "y1": 0
      },
      "cell_type": "number",
      "raw_value": "5.6725",
      "normalized_value": 5.6725,
      "rowspan": 1,
      "colspan": 1,
      "formula_text": null,
      "units": null
    },
    {
      "row_index": 3,
      "col_index": 3,
      "bbox": {
        "x0": 0,
        "y0": 0,
        "x1": 0,
        "y1": 0
      },
      "cell_type": "blank",
      "raw_value": "",
      "normalized_value": "",
      "rowspan": 1,
      "colspan": 1,
      "formula_text": null,
      "units": null
    },
    {
      "row_index": 3,
      "col_index": 4,
      "bbox": {
        "x0": 0,
        "y0": 0,
        "x1": 0,
        "y1": 0
      },
      "cell_type": "text",
      "raw_value": "−0.0350",
      "normalized_value": "−0.0350",
      "rowspan": 1,
      "colspan": 1,
      "formula_text": null,
      "units": null
    },
    {
      "row_index": 3,
      "col_index": 5,
      "bbox": {
        "x0": 0,
        "y0": 0,
        "x1": 0,
        "y1": 0
      },
      "cell_type": "blank",
      "raw_value": "",
      "normalized_value": "",
      "rowspan": 1,
      "colspan": 1,
      "formula_text": null,
      "units": null
    },
    {
      "row_index": 3,
      "col_index": 6,
      "bbox": {
        "x0": 0,
        "y0": 0,
        "x1": 0,
        "y1": 0
      },
      "cell_type": "number",
      "raw_value": "5.7300",
      "normalized_value": 5.73,
      "rowspan": 1,
      "colspan": 1,
      "formula_text": null,
      "units": null
    },
    {
      "row_index": 3,
      "col_index": 7,
      "bbox": {
        "x0": 0,
        "y0": 0,
        "x1": 0,
        "y1": 0
      },
      "cell_type": "blank",
      "raw_value": "",
      "normalized_value": "",
      "rowspan": 1,
      "colspan": 1,
      "formula_text": null,
      "units": null
    },
    {
      "row_index": 3,
      "col_index": 8,
      "bbox": {
        "x0": 0,
        "y0": 0,
        "x1": 0,
        "y1": 0
      },
      "cell_type": "number",
      "raw_value": "5.6350",
      "normalized_value": 5.635,
      "rowspan": 1,
      "colspan": 1,
      "formula_text": null,
      "units": null
    },
    {
      "row_index": 4,
      "col_index": 0,
      "bbox": {
        "x0": 0,
        "y0": 0,
        "x1": 0,
        "y1": 0
      },
      "cell_type": "text",
      "raw_value": "Dec-22",
      "normalized_value": "Dec-22",
      "rowspan": 1,
      "colspan": 1,
      "formula_text": null,
      "units": null
    },
    {
      "row_index": 4,
      "col_index": 1,
      "bbox": {
        "x0": 0,
        "y0": 0,
        "x1": 0,
        "y1": 0
      },
      "cell_type": "blank",
      "raw_value": "",
      "normalized_value": "",
      "rowspan": 1,
      "colspan": 1,
      "formula_text": null,
      "units": null
    },
    {
      "row_index": 4,
      "col_index": 2,
      "bbox": {
        "x0": 0,
        "y0": 0,
        "x1": 0,
        "y1": 0
      },
      "cell_type": "number",
      "raw_value": "4.9575",
      "normalized_value": 4.9575,
      "rowspan": 1,
      "colspan": 1,
      "formula_text": null,
      "units": null
    },
    {
      "row_index": 4,
      "col_index": 3,
      "bbox": {
        "x0": 0,
        "y0": 0,
        "x1": 0,
        "y1": 0
      },
      "cell_type": "blank",
      "raw_value": "",
      "normalized_value": "",
      "rowspan": 1,
      "colspan": 1,
      "formula_text": null,
      "units": null
    },
    {
      "row_index": 4,
      "col_index": 4,
      "bbox": {
        "x0": 0,
        "y0": 0,
        "x1": 0,
        "y1": 0
      },
      "cell_type": "number",
      "raw_value": "0.0175",
      "normalized_value": 0.0175,
      "rowspan": 1,
      "colspan": 1,
      "formula_text": null,
      "units": null
    },
    {
      "row_index": 4,
      "col_index": 5,
      "bbox": {
        "x0": 0,
        "y0": 0,
        "x1": 0,
        "y1": 0
      },
      "cell_type": "blank",
      "raw_value": "",
      "normalized_value": "",
      "rowspan": 1,
      "colspan": 1,
      "formula_text": null,
      "units": null
    },
    {
      "row_index": 4,
      "col_index": 6,
      "bbox": {
        "x0": 0,
        "y0": 0,
        "x1": 0,
        "y1": 0
      },
      "cell_type": "number",
      "raw_value": "4.9750",
      "normalized_value": 4.975,
      "rowspan": 1,
      "colspan": 1,
      "formula_text": null,
      "units": null
    },
    {
      "row_index": 4,
      "col_index": 7,
      "bbox": {
        "x0": 0,
        "y0": 0,
        "x1": 0,
        "y1": 0
      },
      "cell_type": "blank",
      "raw_value": "",
      "normalized_value": "",
      "rowspan": 1,
      "colspan": 1,
      "formula_text": null,
      "units": null
    },
    {
      "row_index": 4,
      "col_index": 8,
      "bbox": {
        "x0": 0,
        "y0": 0,
        "x1": 0,
        "y1": 0
      },
      "cell_type": "number",
      "raw_value": "4.9025",
      "normalized_value": 4.9025,
      "rowspan": 1,
      "colspan": 1,
      "formula_text": null,
      "units": null
    },
    {
      "row_index": 5,
      "col_index": 0,
      "bbox": {
        "x0": 0,
        "y0": 0,
        "x1": 0,
        "y1": 0
      },
      "cell_type": "text",
      "raw_value": "Jul-23",
      "normalized_value": "Jul-23",
      "rowspan": 1,
      "colspan": 1,
      "formula_text": null,
      "units": null
    },
    {
      "row_index": 5,
      "col_index": 1,
      "bbox": {
        "x0": 0,
        "y0": 0,
        "x1": 0,
        "y1": 0
      },
      "cell_type": "blank",
      "raw_value": "",
      "normalized_value": "",
      "rowspan": 1,
      "colspan": 1,
      "formula_text": null,
      "units": null
    },
    {
      "row_index": 5,
      "col_index": 2,
      "bbox": {
        "x0": 0,
        "y0": 0,
        "x1": 0,
        "y1": 0
      },
      "cell_type": "number",
      "raw_value": "5.0400",
      "normalized_value": 5.04,
      "rowspan": 1,
      "colspan": 1,
      "formula_text": null,
      "units": null
    },
    {
      "row_index": 5,
      "col_index": 3,
      "bbox": {
        "x0": 0,
        "y0": 0,
        "x1": 0,
        "y1": 0
      },
      "cell_type": "blank",
      "raw_value": "",
      "normalized_value": "",
      "rowspan": 1,
      "colspan": 1,
      "formula_text": null,
      "units": null
    },
    {
      "row_index": 5,
      "col_index": 4,
      "bbox": {
        "x0": 0,
        "y0": 0,
        "x1": 0,
        "y1": 0
      },
      "cell_type": "text",
      "raw_value": "−0.0300",
      "normalized_value": "−0.0300",
      "rowspan": 1,
      "colspan": 1,
      "formula_text": null,
      "units": null
    },
    {
      "row_index": 5,
      "col_index": 5,
      "bbox": {
        "x0": 0,
        "y0": 0,
        "x1": 0,
        "y1": 0
      },
      "cell_type": "blank",
      "raw_value": "",
      "normalized_value": "",
      "rowspan": 1,
      "colspan": 1,
      "formula_text": null,
      "units": null
    },
    {
      "row_index": 5,
      "col_index": 6,
      "bbox": {
        "x0": 0,
        "y0": 0,
        "x1": 0,
        "y1": 0
      },
      "cell_type": "number",
      "raw_value": "5.0825",
      "normalized_value": 5.0825,
      "rowspan": 1,
      "colspan": 1,
      "formula_text": null,
      "units": null
    },
    {
      "row_index": 5,
      "col_index": 7,
      "bbox": {
        "x0": 0,
        "y0": 0,
        "x1": 0,
        "y1": 0
      },
      "cell_type": "blank",
      "raw_value": "",
      "normalized_value": "",
      "rowspan": 1,
      "colspan": 1,
      "formula_text": null,
      "units": null
    },
    {
      "row_index": 5,
      "col_index": 8,
      "bbox": {
        "x0": 0,
        "y0": 0,
        "x1": 0,
        "y1": 0
      },
      "cell_type": "number",
      "raw_value": "5.0400",
      "normalized_value": 5.04,
      "rowspan": 1,
      "colspan": 1,
      "formula_text": null,
      "units": null
    }
  ],
  "footnotes": [],
  "units": [],
  "formula_cells": [],
  "derived_columns": [],
  "variable_candidates": {},
  "description": "Introduction This table presents bond cashflow information.",
  "table_summary": "Introduction This table presents bond cashflow information.",
  "table_schema_hint": "bond cashflows",
  "linked_concept_ids": [
    "bond_pricing"
  ],
  "links": [
    {
      "link_type": "TABLE_OF",
      "target_id": "bond_pricing",
      "source_anchor": {
        "page_number": 85,
        "bbox": {
          "x0": 175.75,
          "y0": 27.25,
          "x1": 378.57800144999993,
          "y1": 110.41984650000006
        },
        "extractor": "pdfplumber",
        "confidence": 0.9,
        "metadata": {}
      },
      "evidence": "Semantic similarity: 0.63 + Keywords: bond, maturity, cashflow",
      "confidence": 0.8329564452171325
    }
  ],
  "source_anchor": {
    "page_number": 85,
    "bbox": {
      "x0": 175.75,
      "y0": 27.25,
      "x1": 378.57800144999993,
      "y1": 110.41984650000006
    },
    "extractor": "pdfplumber",
    "confidence": 0.9,
    "metadata": {}
  },
  "confidence": 1.0,
  "heading_path": null,
  "page_span": [
    85,
    85
  ]
}