{
  "segment_id": "table_p454_idx0",
  "table_id": null,
  "table_number": null,
  "caption": "",
  "row_headers": [
    [
      "Size: Stock market capitalization"
    ],
    [
      "Book-to-market ratio"
    ],
    [
      "Momentum: Return in past year"
    ],
    [
      "Stock issues: Growth in shares outstanding"
    ],
    [
      "Accruals: Change in net working capital"
    ],
    [
      "Profitability: Return on assets"
    ],
    [
      "Asset growth: Growth in total assets"
    ],
    [
      "Dividend yield"
    ],
    [
      "Beta: Single index model"
    ],
    [
      "Volatility: Standard deviation of stock returns"
    ],
    [
      "Turnover: Shares traded as a fraction of outstanding"
    ],
    [
      "Sales: Total sales as multiple of market capitalization"
    ]
  ],
  "col_headers": [
    "",
    "",
    "Slope",
    "t-Statistic"
  ],
  "cells": [
    [
      "",
      "",
      "Slope",
      "t-Statistic"
    ],
    [
      "Size: Stock market capitalization",
      "",
      "",
      "—5.01"
    ],
    [
      "Book-to-market ratio",
      "",
      "35",
      "6.18"
    ],
    [
      "Momentum: Return in past year",
      "",
      "96",
      "6.86"
    ],
    [
      "Stock issues: Growth in shares outstanding",
      "",
      "-.35",
      ""
    ],
    [
      "Accruals: Change in net working capital",
      "",
      "-1.38",
      "=5.69)"
    ],
    [
      "Profitability: Return on assets",
      "",
      "1.43",
      "3.57"
    ],
    [
      "Asset growth: Growth in total assets",
      "",
      "-.54",
      "-4.49"
    ],
    [
      "Dividend yield",
      "",
      "-.46",
      "-.27"
    ],
    [
      "Beta: Single index model",
      "",
      "ssh",
      "3.05"
    ],
    [
      "Volatility: Standard deviation of stock returns",
      "",
      "-1.45",
      "-1.40"
    ],
    [
      "Turnover: Shares traded as a fraction of outstanding",
      "shares",
      "",
      "-3.68"
    ],
    [
      "Sales: Total sales as multiple of market capitalization",
      "",
      "04",
      "3.10"
    ]
  ],
  "cell_meta": [
    {
      "row_index": 0,
      "col_index": 0,
      "bbox": {
        "x0": 0,
        "y0": 0,
        "x1": 0,
        "y1": 0
      },
      "cell_type": "blank",
      "raw_value": "",
      "normalized_value": "",
      "rowspan": 1,
      "colspan": 1,
      "formula_text": null,
      "units": null
    },
    {
      "row_index": 0,
      "col_index": 1,
      "bbox": {
        "x0": 0,
        "y0": 0,
        "x1": 0,
        "y1": 0
      },
      "cell_type": "blank",
      "raw_value": "",
      "normalized_value": "",
      "rowspan": 1,
      "colspan": 1,
      "formula_text": null,
      "units": null
    },
    {
      "row_index": 0,
      "col_index": 2,
      "bbox": {
        "x0": 710.0,
        "y0": 26.0,
        "x1": 766.0,
        "y1": 45.0
      },
      "cell_type": "text",
      "raw_value": "Slope",
      "normalized_value": "Slope",
      "rowspan": 1,
      "colspan": 1,
      "formula_text": null,
      "units": null
    },
    {
      "row_index": 0,
      "col_index": 3,
      "bbox": {
        "x0": 876.0,
        "y0": 26.0,
        "x1": 970.0,
        "y1": 41.0
      },
      "cell_type": "text",
      "raw_value": "t-Statistic",
      "normalized_value": "t-Statistic",
      "rowspan": 1,
      "colspan": 1,
      "formula_text": null,
      "units": null
    },
    {
      "row_index": 1,
      "col_index": 0,
      "bbox": {
        "x0": 37.0,
        "y0": 68.0,
        "x1": 341.0,
        "y1": 87.0
      },
      "cell_type": "text",
      "raw_value": "Size: Stock market capitalization",
      "normalized_value": "Size: Stock market capitalization",
      "rowspan": 1,
      "colspan": 1,
      "formula_text": null,
      "units": null
    },
    {
      "row_index": 1,
      "col_index": 1,
      "bbox": {
        "x0": 0,
        "y0": 0,
        "x1": 0,
        "y1": 0
      },
      "cell_type": "blank",
      "raw_value": "",
      "normalized_value": "",
      "rowspan": 1,
      "colspan": 1,
      "formula_text": null,
      "units": null
    },
    {
      "row_index": 1,
      "col_index": 2,
      "bbox": {
        "x0": 0,
        "y0": 0,
        "x1": 0,
        "y1": 0
      },
      "cell_type": "blank",
      "raw_value": "",
      "normalized_value": "",
      "rowspan": 1,
      "colspan": 1,
      "formula_text": null,
      "units": null
    },
    {
      "row_index": 1,
      "col_index": 3,
      "bbox": {
        "x0": 900.0,
        "y0": 68.0,
        "x1": 954.0,
        "y1": 83.0
      },
      "cell_type": "text",
      "raw_value": "—5.01",
      "normalized_value": "—5.01",
      "rowspan": 1,
      "colspan": 1,
      "formula_text": null,
      "units": null
    },
    {
      "row_index": 2,
      "col_index": 0,
      "bbox": {
        "x0": 38.0,
        "y0": 105.0,
        "x1": 231.0,
        "y1": 120.0
      },
      "cell_type": "text",
      "raw_value": "Book-to-market ratio",
      "normalized_value": "Book-to-market ratio",
      "rowspan": 1,
      "colspan": 1,
      "formula_text": null,
      "units": null
    },
    {
      "row_index": 2,
      "col_index": 1,
      "bbox": {
        "x0": 0,
        "y0": 0,
        "x1": 0,
        "y1": 0
      },
      "cell_type": "blank",
      "raw_value": "",
      "normalized_value": "",
      "rowspan": 1,
      "colspan": 1,
      "formula_text": null,
      "units": null
    },
    {
      "row_index": 2,
      "col_index": 2,
      "bbox": {
        "x0": 740.0,
        "y0": 105.0,
        "x1": 768.0,
        "y1": 120.0
      },
      "cell_type": "number",
      "raw_value": "35",
      "normalized_value": 35,
      "rowspan": 1,
      "colspan": 1,
      "formula_text": null,
      "units": null
    },
    {
      "row_index": 2,
      "col_index": 3,
      "bbox": {
        "x0": 915.0,
        "y0": 105.0,
        "x1": 957.0,
        "y1": 120.0
      },
      "cell_type": "number",
      "raw_value": "6.18",
      "normalized_value": 6.18,
      "rowspan": 1,
      "colspan": 1,
      "formula_text": null,
      "units": null
    },
    {
      "row_index": 3,
      "col_index": 0,
      "bbox": {
        "x0": 38.0,
        "y0": 142.0,
        "x1": 333.0,
        "y1": 162.0
      },
      "cell_type": "text",
      "raw_value": "Momentum: Return in past year",
      "normalized_value": "Momentum: Return in past year",
      "rowspan": 1,
      "colspan": 1,
      "formula_text": null,
      "units": null
    },
    {
      "row_index": 3,
      "col_index": 1,
      "bbox": {
        "x0": 0,
        "y0": 0,
        "x1": 0,
        "y1": 0
      },
      "cell_type": "blank",
      "raw_value": "",
      "normalized_value": "",
      "rowspan": 1,
      "colspan": 1,
      "formula_text": null,
      "units": null
    },
    {
      "row_index": 3,
      "col_index": 2,
      "bbox": {
        "x0": 740.0,
        "y0": 142.0,
        "x1": 769.0,
        "y1": 157.0
      },
      "cell_type": "number",
      "raw_value": "96",
      "normalized_value": 96,
      "rowspan": 1,
      "colspan": 1,
      "formula_text": null,
      "units": null
    },
    {
      "row_index": 3,
      "col_index": 3,
      "bbox": {
        "x0": 915.0,
        "y0": 142.0,
        "x1": 957.0,
        "y1": 157.0
      },
      "cell_type": "number",
      "raw_value": "6.86",
      "normalized_value": 6.86,
      "rowspan": 1,
      "colspan": 1,
      "formula_text": null,
      "units": null
    },
    {
      "row_index": 4,
      "col_index": 0,
      "bbox": {
        "x0": 37.0,
        "y0": 179.0,
        "x1": 444.0,
        "y1": 199.0
      },
      "cell_type": "text",
      "raw_value": "Stock issues: Growth in shares outstanding",
      "normalized_value": "Stock issues: Growth in shares outstanding",
      "rowspan": 1,
      "colspan": 1,
      "formula_text": null,
      "units": null
    },
    {
      "row_index": 4,
      "col_index": 1,
      "bbox": {
        "x0": 0,
        "y0": 0,
        "x1": 0,
        "y1": 0
      },
      "cell_type": "blank",
      "raw_value": "",
      "normalized_value": "",
      "rowspan": 1,
      "colspan": 1,
      "formula_text": null,
      "units": null
    },
    {
      "row_index": 4,
      "col_index": 2,
      "bbox": {
        "x0": 724.0,
        "y0": 179.0,
        "x1": 768.0,
        "y1": 194.0
      },
      "cell_type": "text",
      "raw_value": "-.35",
      "normalized_value": "-.35",
      "rowspan": 1,
      "colspan": 1,
      "formula_text": null,
      "units": null
    },
    {
      "row_index": 4,
      "col_index": 3,
      "bbox": {
        "x0": 0,
        "y0": 0,
        "x1": 0,
        "y1": 0
      },
      "cell_type": "blank",
      "raw_value": "",
      "normalized_value": "",
      "rowspan": 1,
      "colspan": 1,
      "formula_text": null,
      "units": null
    },
    {
      "row_index": 5,
      "col_index": 0,
      "bbox": {
        "x0": 36.0,
        "y0": 216.0,
        "x1": 412.0,
        "y1": 236.0
      },
      "cell_type": "text",
      "raw_value": "Accruals: Change in net working capital",
      "normalized_value": "Accruals: Change in net working capital",
      "rowspan": 1,
      "colspan": 1,
      "formula_text": null,
      "units": null
    },
    {
      "row_index": 5,
      "col_index": 1,
      "bbox": {
        "x0": 0,
        "y0": 0,
        "x1": 0,
        "y1": 0
      },
      "cell_type": "blank",
      "raw_value": "",
      "normalized_value": "",
      "rowspan": 1,
      "colspan": 1,
      "formula_text": null,
      "units": null
    },
    {
      "row_index": 5,
      "col_index": 2,
      "bbox": {
        "x0": 711.0,
        "y0": 216.0,
        "x1": 768.0,
        "y1": 231.0
      },
      "cell_type": "text",
      "raw_value": "-1.38",
      "normalized_value": "-1.38",
      "rowspan": 1,
      "colspan": 1,
      "formula_text": null,
      "units": null
    },
    {
      "row_index": 5,
      "col_index": 3,
      "bbox": {
        "x0": 900.0,
        "y0": 216.0,
        "x1": 957.0,
        "y1": 231.0
      },
      "cell_type": "formula",
      "raw_value": "=5.69)",
      "normalized_value": "=5.69)",
      "rowspan": 1,
      "colspan": 1,
      "formula_text": null,
      "units": null
    },
    {
      "row_index": 6,
      "col_index": 0,
      "bbox": {
        "x0": 38.0,
        "y0": 253.0,
        "x1": 309.0,
        "y1": 273.0
      },
      "cell_type": "text",
      "raw_value": "Profitability: Return on assets",
      "normalized_value": "Profitability: Return on assets",
      "rowspan": 1,
      "colspan": 1,
      "formula_text": null,
      "units": null
    },
    {
      "row_index": 6,
      "col_index": 1,
      "bbox": {
        "x0": 0,
        "y0": 0,
        "x1": 0,
        "y1": 0
      },
      "cell_type": "blank",
      "raw_value": "",
      "normalized_value": "",
      "rowspan": 1,
      "colspan": 1,
      "formula_text": null,
      "units": null
    },
    {
      "row_index": 6,
      "col_index": 2,
      "bbox": {
        "x0": 729.0,
        "y0": 253.0,
        "x1": 768.0,
        "y1": 268.0
      },
      "cell_type": "number",
      "raw_value": "1.43",
      "normalized_value": 1.43,
      "rowspan": 1,
      "colspan": 1,
      "formula_text": null,
      "units": null
    },
    {
      "row_index": 6,
      "col_index": 3,
      "bbox": {
        "x0": 916.0,
        "y0": 253.0,
        "x1": 957.0,
        "y1": 268.0
      },
      "cell_type": "number",
      "raw_value": "3.57",
      "normalized_value": 3.57,
      "rowspan": 1,
      "colspan": 1,
      "formula_text": null,
      "units": null
    },
    {
      "row_index": 7,
      "col_index": 0,
      "bbox": {
        "x0": 36.0,
        "y0": 290.0,
        "x1": 377.0,
        "y1": 310.0
      },
      "cell_type": "text",
      "raw_value": "Asset growth: Growth in total assets",
      "normalized_value": "Asset growth: Growth in total assets",
      "rowspan": 1,
      "colspan": 1,
      "formula_text": null,
      "units": null
    },
    {
      "row_index": 7,
      "col_index": 1,
      "bbox": {
        "x0": 0,
        "y0": 0,
        "x1": 0,
        "y1": 0
      },
      "cell_type": "blank",
      "raw_value": "",
      "normalized_value": "",
      "rowspan": 1,
      "colspan": 1,
      "formula_text": null,
      "units": null
    },
    {
      "row_index": 7,
      "col_index": 2,
      "bbox": {
        "x0": 724.0,
        "y0": 290.0,
        "x1": 768.0,
        "y1": 305.0
      },
      "cell_type": "text",
      "raw_value": "-.54",
      "normalized_value": "-.54",
      "rowspan": 1,
      "colspan": 1,
      "formula_text": null,
      "units": null
    },
    {
      "row_index": 7,
      "col_index": 3,
      "bbox": {
        "x0": 900.0,
        "y0": 290.0,
        "x1": 957.0,
        "y1": 305.0
      },
      "cell_type": "text",
      "raw_value": "-4.49",
      "normalized_value": "-4.49",
      "rowspan": 1,
      "colspan": 1,
      "formula_text": null,
      "units": null
    },
    {
      "row_index": 8,
      "col_index": 0,
      "bbox": {
        "x0": 38.0,
        "y0": 327.0,
        "x1": 171.0,
        "y1": 347.0
      },
      "cell_type": "text",
      "raw_value": "Dividend yield",
      "normalized_value": "Dividend yield",
      "rowspan": 1,
      "colspan": 1,
      "formula_text": null,
      "units": null
    },
    {
      "row_index": 8,
      "col_index": 1,
      "bbox": {
        "x0": 0,
        "y0": 0,
        "x1": 0,
        "y1": 0
      },
      "cell_type": "blank",
      "raw_value": "",
      "normalized_value": "",
      "rowspan": 1,
      "colspan": 1,
      "formula_text": null,
      "units": null
    },
    {
      "row_index": 8,
      "col_index": 2,
      "bbox": {
        "x0": 724.0,
        "y0": 327.0,
        "x1": 769.0,
        "y1": 342.0
      },
      "cell_type": "text",
      "raw_value": "-.46",
      "normalized_value": "-.46",
      "rowspan": 1,
      "colspan": 1,
      "formula_text": null,
      "units": null
    },
    {
      "row_index": 8,
      "col_index": 3,
      "bbox": {
        "x0": 913.0,
        "y0": 327.0,
        "x1": 957.0,
        "y1": 342.0
      },
      "cell_type": "text",
      "raw_value": "-.27",
      "normalized_value": "-.27",
      "rowspan": 1,
      "colspan": 1,
      "formula_text": null,
      "units": null
    },
    {
      "row_index": 9,
      "col_index": 0,
      "bbox": {
        "x0": 38.0,
        "y0": 364.0,
        "x1": 273.0,
        "y1": 384.0
      },
      "cell_type": "text",
      "raw_value": "Beta: Single index model",
      "normalized_value": "Beta: Single index model",
      "rowspan": 1,
      "colspan": 1,
      "formula_text": null,
      "units": null
    },
    {
      "row_index": 9,
      "col_index": 1,
      "bbox": {
        "x0": 0,
        "y0": 0,
        "x1": 0,
        "y1": 0
      },
      "cell_type": "blank",
      "raw_value": "",
      "normalized_value": "",
      "rowspan": 1,
      "colspan": 1,
      "formula_text": null,
      "units": null
    },
    {
      "row_index": 9,
      "col_index": 2,
      "bbox": {
        "x0": 740.0,
        "y0": 360.0,
        "x1": 771.0,
        "y1": 388.0
      },
      "cell_type": "text",
      "raw_value": "ssh",
      "normalized_value": "ssh",
      "rowspan": 1,
      "colspan": 1,
      "formula_text": null,
      "units": null
    },
    {
      "row_index": 9,
      "col_index": 3,
      "bbox": {
        "x0": 916.0,
        "y0": 364.0,
        "x1": 957.0,
        "y1": 379.0
      },
      "cell_type": "number",
      "raw_value": "3.05",
      "normalized_value": 3.05,
      "rowspan": 1,
      "colspan": 1,
      "formula_text": null,
      "units": null
    },
    {
      "row_index": 10,
      "col_index": 0,
      "bbox": {
        "x0": 36.0,
        "y0": 401.0,
        "x1": 459.0,
        "y1": 421.0
      },
      "cell_type": "text",
      "raw_value": "Volatility: Standard deviation of stock returns",
      "normalized_value": "Volatility: Standard deviation of stock returns",
      "rowspan": 1,
      "colspan": 1,
      "formula_text": null,
      "units": null
    },
    {
      "row_index": 10,
      "col_index": 1,
      "bbox": {
        "x0": 0,
        "y0": 0,
        "x1": 0,
        "y1": 0
      },
      "cell_type": "blank",
      "raw_value": "",
      "normalized_value": "",
      "rowspan": 1,
      "colspan": 1,
      "formula_text": null,
      "units": null
    },
    {
      "row_index": 10,
      "col_index": 2,
      "bbox": {
        "x0": 711.0,
        "y0": 401.0,
        "x1": 768.0,
        "y1": 416.0
      },
      "cell_type": "text",
      "raw_value": "-1.45",
      "normalized_value": "-1.45",
      "rowspan": 1,
      "colspan": 1,
      "formula_text": null,
      "units": null
    },
    {
      "row_index": 10,
      "col_index": 3,
      "bbox": {
        "x0": 900.0,
        "y0": 401.0,
        "x1": 957.0,
        "y1": 416.0
      },
      "cell_type": "text",
      "raw_value": "-1.40",
      "normalized_value": "-1.40",
      "rowspan": 1,
      "colspan": 1,
      "formula_text": null,
      "units": null
    },
    {
      "row_index": 11,
      "col_index": 0,
      "bbox": {
        "x0": 37.0,
        "y0": 434.0,
        "x1": 529.0,
        "y1": 462.0
      },
      "cell_type": "text",
      "raw_value": "Turnover: Shares traded as a fraction of outstanding",
      "normalized_value": "Turnover: Shares traded as a fraction of outstanding",
      "rowspan": 1,
      "colspan": 1,
      "formula_text": null,
      "units": null
    },
    {
      "row_index": 11,
      "col_index": 1,
      "bbox": {
        "x0": 537.0,
        "y0": 438.0,
        "x1": 599.0,
        "y1": 453.0
      },
      "cell_type": "text",
      "raw_value": "shares",
      "normalized_value": "shares",
      "rowspan": 1,
      "colspan": 1,
      "formula_text": null,
      "units": null
    },
    {
      "row_index": 11,
      "col_index": 2,
      "bbox": {
        "x0": 0,
        "y0": 0,
        "x1": 0,
        "y1": 0
      },
      "cell_type": "blank",
      "raw_value": "",
      "normalized_value": "",
      "rowspan": 1,
      "colspan": 1,
      "formula_text": null,
      "units": null
    },
    {
      "row_index": 11,
      "col_index": 3,
      "bbox": {
        "x0": 900.0,
        "y0": 438.0,
        "x1": 957.0,
        "y1": 453.0
      },
      "cell_type": "text",
      "raw_value": "-3.68",
      "normalized_value": "-3.68",
      "rowspan": 1,
      "colspan": 1,
      "formula_text": null,
      "units": null
    },
    {
      "row_index": 12,
      "col_index": 0,
      "bbox": {
        "x0": 37.0,
        "y0": 475.0,
        "x1": 532.0,
        "y1": 494.0
      },
      "cell_type": "text",
      "raw_value": "Sales: Total sales as multiple of market capitalization",
      "normalized_value": "Sales: Total sales as multiple of market capitalization",
      "rowspan": 1,
      "colspan": 1,
      "formula_text": null,
      "units": null
    },
    {
      "row_index": 12,
      "col_index": 1,
      "bbox": {
        "x0": 0,
        "y0": 0,
        "x1": 0,
        "y1": 0
      },
      "cell_type": "blank",
      "raw_value": "",
      "normalized_value": "",
      "rowspan": 1,
      "colspan": 1,
      "formula_text": null,
      "units": null
    },
    {
      "row_index": 12,
      "col_index": 2,
      "bbox": {
        "x0": 740.0,
        "y0": 475.0,
        "x1": 768.0,
        "y1": 490.0
      },
      "cell_type": "number",
      "raw_value": "04",
      "normalized_value": 4,
      "rowspan": 1,
      "colspan": 1,
      "formula_text": null,
      "units": null
    },
    {
      "row_index": 12,
      "col_index": 3,
      "bbox": {
        "x0": 916.0,
        "y0": 475.0,
        "x1": 957.0,
        "y1": 490.0
      },
      "cell_type": "number",
      "raw_value": "3.10",
      "normalized_value": 3.1,
      "rowspan": 1,
      "colspan": 1,
      "formula_text": null,
      "units": null
    }
  ],
  "footnotes": [],
  "units": [],
  "formula_cells": [],
  "derived_columns": [],
  "variable_candidates": {},
  "description": "",
  "table_summary": "",
  "table_schema_hint": null,
  "linked_concept_ids": [],
  "links": [],
  "source_anchor": {
    "page_number": 454,
    "bbox": {
      "x0": 36.0,
      "y0": 26.0,
      "x1": 970.0,
      "y1": 494.0
    },
    "extractor": "ocr_image",
    "confidence": 0.6,
    "metadata": {}
  },
  "confidence": 1.0,
  "heading_path": "Part III: Equilibrium in Capital Markets > Table 13.3 > 13.3: Fama-French-Type Factor Models > The Factor Zoo",
  "page_span": [
    454,
    454
  ],
  "source_chunk_id": "chunk_03560",
  "page_start": 454,
  "page_end": 454
}