{
  "segment_id": "table_p906_idx278",
  "table_id": null,
  "table_number": null,
  "caption": "CHAPTER 25",
  "row_headers": [
    [
      ""
    ],
    [
      ""
    ],
    [
      ""
    ],
    [
      ""
    ],
    [
      ""
    ],
    [
      ""
    ],
    [
      ""
    ],
    [
      ""
    ],
    [
      ""
    ],
    [
      ""
    ],
    [
      ""
    ],
    [
      ""
    ],
    [
      ""
    ],
    [
      ""
    ],
    [
      ""
    ],
    [
      ""
    ]
  ],
  "col_headers": [
    "",
    "",
    "",
    "Beta against\nMSCI World",
    "",
    "",
    "",
    "Residual Standard\nDeviation",
    "",
    "",
    ""
  ],
  "cells": [
    [
      "",
      "",
      "",
      "Beta against\nMSCI World",
      "",
      "",
      "",
      "Residual Standard\nDeviation",
      "",
      "",
      ""
    ],
    [
      "",
      "",
      "",
      "Local\nCurrency",
      "",
      "Dollar-\nDenominated",
      "",
      "Local\nCurrency",
      "",
      "Dollar-\nDenominated",
      ""
    ],
    [
      "",
      "U.S. (S&P 500)",
      "",
      "1.123",
      "",
      "0.987",
      "",
      "0.011",
      "",
      "0.008",
      ""
    ],
    [
      "",
      "China (Shanghai)",
      "",
      "0.702",
      "",
      "0.628",
      "",
      "0.031",
      "",
      "0.040",
      ""
    ],
    [
      "",
      "Eurozone (Euronext)",
      "",
      "1.030",
      "",
      "1.024",
      "",
      "0.022",
      "",
      "0.023",
      ""
    ],
    [
      "",
      "U.K. (FTSE)",
      "",
      "0.795",
      "",
      "0.952",
      "",
      "0.024",
      "",
      "0.022",
      ""
    ],
    [
      "",
      "Hong Kong (Hang Seng)",
      "",
      "0.895",
      "",
      "0.707",
      "",
      "0.033",
      "",
      "0.037",
      ""
    ],
    [
      "",
      "India (BSE)",
      "",
      "0.927",
      "",
      "0.902",
      "",
      "0.040",
      "",
      "0.049",
      ""
    ],
    [
      "",
      "Japan (Nikkei)",
      "",
      "0.952",
      "",
      "0.748",
      "",
      "0.028",
      "",
      "0.026",
      ""
    ],
    [
      "",
      "Korea (KOSPI)",
      "",
      "1.032",
      "",
      "1.024",
      "",
      "0.030",
      "",
      "0.039",
      ""
    ],
    [
      "",
      "Swiss (SMI)",
      "",
      "0.637",
      "",
      "0.627",
      "",
      "0.022",
      "",
      "0.023",
      ""
    ],
    [
      "",
      "Canada (TSX)",
      "",
      "1.205",
      "",
      "1.030",
      "",
      "0.022",
      "",
      "0.020",
      ""
    ],
    [
      "",
      "MSCI-Arabian",
      "",
      "0.640",
      "",
      "",
      "",
      "0.136",
      "",
      "",
      ""
    ],
    [
      "",
      "MSCI-Latin Amer",
      "",
      "1.323",
      "",
      "",
      "",
      "0.146",
      "",
      "",
      ""
    ],
    [
      "",
      "MSCI-World",
      "",
      "1.000",
      "",
      "",
      "",
      "0.000",
      "",
      "",
      ""
    ],
    [
      "",
      "Mean",
      "",
      "0.930",
      "",
      "0.863",
      "",
      "0.026",
      "",
      "0.029",
      ""
    ],
    [
      "",
      "Median",
      "",
      "0.939",
      "",
      "0.927",
      "",
      "0.026",
      "",
      "0.024",
      ""
    ]
  ],
  "cell_meta": [
    {
      "row_index": 0,
      "col_index": 0,
      "bbox": {
        "x0": 0,
        "y0": 0,
        "x1": 0,
        "y1": 0
      },
      "cell_type": "blank",
      "raw_value": "",
      "normalized_value": "",
      "rowspan": 1,
      "colspan": 1,
      "formula_text": null,
      "units": null
    },
    {
      "row_index": 0,
      "col_index": 1,
      "bbox": {
        "x0": 0,
        "y0": 0,
        "x1": 0,
        "y1": 0
      },
      "cell_type": "blank",
      "raw_value": "",
      "normalized_value": "",
      "rowspan": 1,
      "colspan": 1,
      "formula_text": null,
      "units": null
    },
    {
      "row_index": 0,
      "col_index": 2,
      "bbox": {
        "x0": 0,
        "y0": 0,
        "x1": 0,
        "y1": 0
      },
      "cell_type": "blank",
      "raw_value": "",
      "normalized_value": "",
      "rowspan": 1,
      "colspan": 1,
      "formula_text": null,
      "units": null
    },
    {
      "row_index": 0,
      "col_index": 3,
      "bbox": {
        "x0": 0,
        "y0": 0,
        "x1": 0,
        "y1": 0
      },
      "cell_type": "text",
      "raw_value": "Beta against\nMSCI World",
      "normalized_value": "Beta against\nMSCI World",
      "rowspan": 1,
      "colspan": 1,
      "formula_text": null,
      "units": null
    },
    {
      "row_index": 0,
      "col_index": 4,
      "bbox": {
        "x0": 0,
        "y0": 0,
        "x1": 0,
        "y1": 0
      },
      "cell_type": "blank",
      "raw_value": "",
      "normalized_value": "",
      "rowspan": 1,
      "colspan": 1,
      "formula_text": null,
      "units": null
    },
    {
      "row_index": 0,
      "col_index": 5,
      "bbox": {
        "x0": 0,
        "y0": 0,
        "x1": 0,
        "y1": 0
      },
      "cell_type": "blank",
      "raw_value": "",
      "normalized_value": "",
      "rowspan": 1,
      "colspan": 1,
      "formula_text": null,
      "units": null
    },
    {
      "row_index": 0,
      "col_index": 6,
      "bbox": {
        "x0": 0,
        "y0": 0,
        "x1": 0,
        "y1": 0
      },
      "cell_type": "blank",
      "raw_value": "",
      "normalized_value": "",
      "rowspan": 1,
      "colspan": 1,
      "formula_text": null,
      "units": null
    },
    {
      "row_index": 0,
      "col_index": 7,
      "bbox": {
        "x0": 0,
        "y0": 0,
        "x1": 0,
        "y1": 0
      },
      "cell_type": "text",
      "raw_value": "Residual Standard\nDeviation",
      "normalized_value": "Residual Standard\nDeviation",
      "rowspan": 1,
      "colspan": 1,
      "formula_text": null,
      "units": null
    },
    {
      "row_index": 0,
      "col_index": 8,
      "bbox": {
        "x0": 0,
        "y0": 0,
        "x1": 0,
        "y1": 0
      },
      "cell_type": "blank",
      "raw_value": "",
      "normalized_value": "",
      "rowspan": 1,
      "colspan": 1,
      "formula_text": null,
      "units": null
    },
    {
      "row_index": 0,
      "col_index": 9,
      "bbox": {
        "x0": 0,
        "y0": 0,
        "x1": 0,
        "y1": 0
      },
      "cell_type": "blank",
      "raw_value": "",
      "normalized_value": "",
      "rowspan": 1,
      "colspan": 1,
      "formula_text": null,
      "units": null
    },
    {
      "row_index": 0,
      "col_index": 10,
      "bbox": {
        "x0": 0,
        "y0": 0,
        "x1": 0,
        "y1": 0
      },
      "cell_type": "blank",
      "raw_value": "",
      "normalized_value": "",
      "rowspan": 1,
      "colspan": 1,
      "formula_text": null,
      "units": null
    },
    {
      "row_index": 1,
      "col_index": 0,
      "bbox": {
        "x0": 0,
        "y0": 0,
        "x1": 0,
        "y1": 0
      },
      "cell_type": "blank",
      "raw_value": "",
      "normalized_value": "",
      "rowspan": 1,
      "colspan": 1,
      "formula_text": null,
      "units": null
    },
    {
      "row_index": 1,
      "col_index": 1,
      "bbox": {
        "x0": 0,
        "y0": 0,
        "x1": 0,
        "y1": 0
      },
      "cell_type": "blank",
      "raw_value": "",
      "normalized_value": "",
      "rowspan": 1,
      "colspan": 1,
      "formula_text": null,
      "units": null
    },
    {
      "row_index": 1,
      "col_index": 2,
      "bbox": {
        "x0": 0,
        "y0": 0,
        "x1": 0,
        "y1": 0
      },
      "cell_type": "blank",
      "raw_value": "",
      "normalized_value": "",
      "rowspan": 1,
      "colspan": 1,
      "formula_text": null,
      "units": null
    },
    {
      "row_index": 1,
      "col_index": 3,
      "bbox": {
        "x0": 0,
        "y0": 0,
        "x1": 0,
        "y1": 0
      },
      "cell_type": "text",
      "raw_value": "Local\nCurrency",
      "normalized_value": "Local\nCurrency",
      "rowspan": 1,
      "colspan": 1,
      "formula_text": null,
      "units": null
    },
    {
      "row_index": 1,
      "col_index": 4,
      "bbox": {
        "x0": 0,
        "y0": 0,
        "x1": 0,
        "y1": 0
      },
      "cell_type": "blank",
      "raw_value": "",
      "normalized_value": "",
      "rowspan": 1,
      "colspan": 1,
      "formula_text": null,
      "units": null
    },
    {
      "row_index": 1,
      "col_index": 5,
      "bbox": {
        "x0": 0,
        "y0": 0,
        "x1": 0,
        "y1": 0
      },
      "cell_type": "text",
      "raw_value": "Dollar-\nDenominated",
      "normalized_value": "Dollar-\nDenominated",
      "rowspan": 1,
      "colspan": 1,
      "formula_text": null,
      "units": null
    },
    {
      "row_index": 1,
      "col_index": 6,
      "bbox": {
        "x0": 0,
        "y0": 0,
        "x1": 0,
        "y1": 0
      },
      "cell_type": "blank",
      "raw_value": "",
      "normalized_value": "",
      "rowspan": 1,
      "colspan": 1,
      "formula_text": null,
      "units": null
    },
    {
      "row_index": 1,
      "col_index": 7,
      "bbox": {
        "x0": 0,
        "y0": 0,
        "x1": 0,
        "y1": 0
      },
      "cell_type": "text",
      "raw_value": "Local\nCurrency",
      "normalized_value": "Local\nCurrency",
      "rowspan": 1,
      "colspan": 1,
      "formula_text": null,
      "units": null
    },
    {
      "row_index": 1,
      "col_index": 8,
      "bbox": {
        "x0": 0,
        "y0": 0,
        "x1": 0,
        "y1": 0
      },
      "cell_type": "blank",
      "raw_value": "",
      "normalized_value": "",
      "rowspan": 1,
      "colspan": 1,
      "formula_text": null,
      "units": null
    },
    {
      "row_index": 1,
      "col_index": 9,
      "bbox": {
        "x0": 0,
        "y0": 0,
        "x1": 0,
        "y1": 0
      },
      "cell_type": "text",
      "raw_value": "Dollar-\nDenominated",
      "normalized_value": "Dollar-\nDenominated",
      "rowspan": 1,
      "colspan": 1,
      "formula_text": null,
      "units": null
    },
    {
      "row_index": 1,
      "col_index": 10,
      "bbox": {
        "x0": 0,
        "y0": 0,
        "x1": 0,
        "y1": 0
      },
      "cell_type": "blank",
      "raw_value": "",
      "normalized_value": "",
      "rowspan": 1,
      "colspan": 1,
      "formula_text": null,
      "units": null
    },
    {
      "row_index": 2,
      "col_index": 0,
      "bbox": {
        "x0": 0,
        "y0": 0,
        "x1": 0,
        "y1": 0
      },
      "cell_type": "blank",
      "raw_value": "",
      "normalized_value": "",
      "rowspan": 1,
      "colspan": 1,
      "formula_text": null,
      "units": null
    },
    {
      "row_index": 2,
      "col_index": 1,
      "bbox": {
        "x0": 0,
        "y0": 0,
        "x1": 0,
        "y1": 0
      },
      "cell_type": "text",
      "raw_value": "U.S. (S&P 500)",
      "normalized_value": "U.S. (S&P 500)",
      "rowspan": 1,
      "colspan": 1,
      "formula_text": null,
      "units": null
    },
    {
      "row_index": 2,
      "col_index": 2,
      "bbox": {
        "x0": 0,
        "y0": 0,
        "x1": 0,
        "y1": 0
      },
      "cell_type": "blank",
      "raw_value": "",
      "normalized_value": "",
      "rowspan": 1,
      "colspan": 1,
      "formula_text": null,
      "units": null
    },
    {
      "row_index": 2,
      "col_index": 3,
      "bbox": {
        "x0": 0,
        "y0": 0,
        "x1": 0,
        "y1": 0
      },
      "cell_type": "number",
      "raw_value": "1.123",
      "normalized_value": 1.123,
      "rowspan": 1,
      "colspan": 1,
      "formula_text": null,
      "units": null
    },
    {
      "row_index": 2,
      "col_index": 4,
      "bbox": {
        "x0": 0,
        "y0": 0,
        "x1": 0,
        "y1": 0
      },
      "cell_type": "blank",
      "raw_value": "",
      "normalized_value": "",
      "rowspan": 1,
      "colspan": 1,
      "formula_text": null,
      "units": null
    },
    {
      "row_index": 2,
      "col_index": 5,
      "bbox": {
        "x0": 0,
        "y0": 0,
        "x1": 0,
        "y1": 0
      },
      "cell_type": "number",
      "raw_value": "0.987",
      "normalized_value": 0.987,
      "rowspan": 1,
      "colspan": 1,
      "formula_text": null,
      "units": null
    },
    {
      "row_index": 2,
      "col_index": 6,
      "bbox": {
        "x0": 0,
        "y0": 0,
        "x1": 0,
        "y1": 0
      },
      "cell_type": "blank",
      "raw_value": "",
      "normalized_value": "",
      "rowspan": 1,
      "colspan": 1,
      "formula_text": null,
      "units": null
    },
    {
      "row_index": 2,
      "col_index": 7,
      "bbox": {
        "x0": 0,
        "y0": 0,
        "x1": 0,
        "y1": 0
      },
      "cell_type": "number",
      "raw_value": "0.011",
      "normalized_value": 0.011,
      "rowspan": 1,
      "colspan": 1,
      "formula_text": null,
      "units": null
    },
    {
      "row_index": 2,
      "col_index": 8,
      "bbox": {
        "x0": 0,
        "y0": 0,
        "x1": 0,
        "y1": 0
      },
      "cell_type": "blank",
      "raw_value": "",
      "normalized_value": "",
      "rowspan": 1,
      "colspan": 1,
      "formula_text": null,
      "units": null
    },
    {
      "row_index": 2,
      "col_index": 9,
      "bbox": {
        "x0": 0,
        "y0": 0,
        "x1": 0,
        "y1": 0
      },
      "cell_type": "number",
      "raw_value": "0.008",
      "normalized_value": 0.008,
      "rowspan": 1,
      "colspan": 1,
      "formula_text": null,
      "units": null
    },
    {
      "row_index": 2,
      "col_index": 10,
      "bbox": {
        "x0": 0,
        "y0": 0,
        "x1": 0,
        "y1": 0
      },
      "cell_type": "blank",
      "raw_value": "",
      "normalized_value": "",
      "rowspan": 1,
      "colspan": 1,
      "formula_text": null,
      "units": null
    },
    {
      "row_index": 3,
      "col_index": 0,
      "bbox": {
        "x0": 0,
        "y0": 0,
        "x1": 0,
        "y1": 0
      },
      "cell_type": "blank",
      "raw_value": "",
      "normalized_value": "",
      "rowspan": 1,
      "colspan": 1,
      "formula_text": null,
      "units": null
    },
    {
      "row_index": 3,
      "col_index": 1,
      "bbox": {
        "x0": 0,
        "y0": 0,
        "x1": 0,
        "y1": 0
      },
      "cell_type": "text",
      "raw_value": "China (Shanghai)",
      "normalized_value": "China (Shanghai)",
      "rowspan": 1,
      "colspan": 1,
      "formula_text": null,
      "units": null
    },
    {
      "row_index": 3,
      "col_index": 2,
      "bbox": {
        "x0": 0,
        "y0": 0,
        "x1": 0,
        "y1": 0
      },
      "cell_type": "blank",
      "raw_value": "",
      "normalized_value": "",
      "rowspan": 1,
      "colspan": 1,
      "formula_text": null,
      "units": null
    },
    {
      "row_index": 3,
      "col_index": 3,
      "bbox": {
        "x0": 0,
        "y0": 0,
        "x1": 0,
        "y1": 0
      },
      "cell_type": "number",
      "raw_value": "0.702",
      "normalized_value": 0.702,
      "rowspan": 1,
      "colspan": 1,
      "formula_text": null,
      "units": null
    },
    {
      "row_index": 3,
      "col_index": 4,
      "bbox": {
        "x0": 0,
        "y0": 0,
        "x1": 0,
        "y1": 0
      },
      "cell_type": "blank",
      "raw_value": "",
      "normalized_value": "",
      "rowspan": 1,
      "colspan": 1,
      "formula_text": null,
      "units": null
    },
    {
      "row_index": 3,
      "col_index": 5,
      "bbox": {
        "x0": 0,
        "y0": 0,
        "x1": 0,
        "y1": 0
      },
      "cell_type": "number",
      "raw_value": "0.628",
      "normalized_value": 0.628,
      "rowspan": 1,
      "colspan": 1,
      "formula_text": null,
      "units": null
    },
    {
      "row_index": 3,
      "col_index": 6,
      "bbox": {
        "x0": 0,
        "y0": 0,
        "x1": 0,
        "y1": 0
      },
      "cell_type": "blank",
      "raw_value": "",
      "normalized_value": "",
      "rowspan": 1,
      "colspan": 1,
      "formula_text": null,
      "units": null
    },
    {
      "row_index": 3,
      "col_index": 7,
      "bbox": {
        "x0": 0,
        "y0": 0,
        "x1": 0,
        "y1": 0
      },
      "cell_type": "number",
      "raw_value": "0.031",
      "normalized_value": 0.031,
      "rowspan": 1,
      "colspan": 1,
      "formula_text": null,
      "units": null
    },
    {
      "row_index": 3,
      "col_index": 8,
      "bbox": {
        "x0": 0,
        "y0": 0,
        "x1": 0,
        "y1": 0
      },
      "cell_type": "blank",
      "raw_value": "",
      "normalized_value": "",
      "rowspan": 1,
      "colspan": 1,
      "formula_text": null,
      "units": null
    },
    {
      "row_index": 3,
      "col_index": 9,
      "bbox": {
        "x0": 0,
        "y0": 0,
        "x1": 0,
        "y1": 0
      },
      "cell_type": "number",
      "raw_value": "0.040",
      "normalized_value": 0.04,
      "rowspan": 1,
      "colspan": 1,
      "formula_text": null,
      "units": null
    },
    {
      "row_index": 3,
      "col_index": 10,
      "bbox": {
        "x0": 0,
        "y0": 0,
        "x1": 0,
        "y1": 0
      },
      "cell_type": "blank",
      "raw_value": "",
      "normalized_value": "",
      "rowspan": 1,
      "colspan": 1,
      "formula_text": null,
      "units": null
    },
    {
      "row_index": 4,
      "col_index": 0,
      "bbox": {
        "x0": 0,
        "y0": 0,
        "x1": 0,
        "y1": 0
      },
      "cell_type": "blank",
      "raw_value": "",
      "normalized_value": "",
      "rowspan": 1,
      "colspan": 1,
      "formula_text": null,
      "units": null
    },
    {
      "row_index": 4,
      "col_index": 1,
      "bbox": {
        "x0": 0,
        "y0": 0,
        "x1": 0,
        "y1": 0
      },
      "cell_type": "text",
      "raw_value": "Eurozone (Euronext)",
      "normalized_value": "Eurozone (Euronext)",
      "rowspan": 1,
      "colspan": 1,
      "formula_text": null,
      "units": null
    },
    {
      "row_index": 4,
      "col_index": 2,
      "bbox": {
        "x0": 0,
        "y0": 0,
        "x1": 0,
        "y1": 0
      },
      "cell_type": "blank",
      "raw_value": "",
      "normalized_value": "",
      "rowspan": 1,
      "colspan": 1,
      "formula_text": null,
      "units": null
    },
    {
      "row_index": 4,
      "col_index": 3,
      "bbox": {
        "x0": 0,
        "y0": 0,
        "x1": 0,
        "y1": 0
      },
      "cell_type": "number",
      "raw_value": "1.030",
      "normalized_value": 1.03,
      "rowspan": 1,
      "colspan": 1,
      "formula_text": null,
      "units": null
    },
    {
      "row_index": 4,
      "col_index": 4,
      "bbox": {
        "x0": 0,
        "y0": 0,
        "x1": 0,
        "y1": 0
      },
      "cell_type": "blank",
      "raw_value": "",
      "normalized_value": "",
      "rowspan": 1,
      "colspan": 1,
      "formula_text": null,
      "units": null
    },
    {
      "row_index": 4,
      "col_index": 5,
      "bbox": {
        "x0": 0,
        "y0": 0,
        "x1": 0,
        "y1": 0
      },
      "cell_type": "number",
      "raw_value": "1.024",
      "normalized_value": 1.024,
      "rowspan": 1,
      "colspan": 1,
      "formula_text": null,
      "units": null
    },
    {
      "row_index": 4,
      "col_index": 6,
      "bbox": {
        "x0": 0,
        "y0": 0,
        "x1": 0,
        "y1": 0
      },
      "cell_type": "blank",
      "raw_value": "",
      "normalized_value": "",
      "rowspan": 1,
      "colspan": 1,
      "formula_text": null,
      "units": null
    },
    {
      "row_index": 4,
      "col_index": 7,
      "bbox": {
        "x0": 0,
        "y0": 0,
        "x1": 0,
        "y1": 0
      },
      "cell_type": "number",
      "raw_value": "0.022",
      "normalized_value": 0.022,
      "rowspan": 1,
      "colspan": 1,
      "formula_text": null,
      "units": null
    },
    {
      "row_index": 4,
      "col_index": 8,
      "bbox": {
        "x0": 0,
        "y0": 0,
        "x1": 0,
        "y1": 0
      },
      "cell_type": "blank",
      "raw_value": "",
      "normalized_value": "",
      "rowspan": 1,
      "colspan": 1,
      "formula_text": null,
      "units": null
    },
    {
      "row_index": 4,
      "col_index": 9,
      "bbox": {
        "x0": 0,
        "y0": 0,
        "x1": 0,
        "y1": 0
      },
      "cell_type": "number",
      "raw_value": "0.023",
      "normalized_value": 0.023,
      "rowspan": 1,
      "colspan": 1,
      "formula_text": null,
      "units": null
    },
    {
      "row_index": 4,
      "col_index": 10,
      "bbox": {
        "x0": 0,
        "y0": 0,
        "x1": 0,
        "y1": 0
      },
      "cell_type": "blank",
      "raw_value": "",
      "normalized_value": "",
      "rowspan": 1,
      "colspan": 1,
      "formula_text": null,
      "units": null
    },
    {
      "row_index": 5,
      "col_index": 0,
      "bbox": {
        "x0": 0,
        "y0": 0,
        "x1": 0,
        "y1": 0
      },
      "cell_type": "blank",
      "raw_value": "",
      "normalized_value": "",
      "rowspan": 1,
      "colspan": 1,
      "formula_text": null,
      "units": null
    },
    {
      "row_index": 5,
      "col_index": 1,
      "bbox": {
        "x0": 0,
        "y0": 0,
        "x1": 0,
        "y1": 0
      },
      "cell_type": "text",
      "raw_value": "U.K. (FTSE)",
      "normalized_value": "U.K. (FTSE)",
      "rowspan": 1,
      "colspan": 1,
      "formula_text": null,
      "units": null
    },
    {
      "row_index": 5,
      "col_index": 2,
      "bbox": {
        "x0": 0,
        "y0": 0,
        "x1": 0,
        "y1": 0
      },
      "cell_type": "blank",
      "raw_value": "",
      "normalized_value": "",
      "rowspan": 1,
      "colspan": 1,
      "formula_text": null,
      "units": null
    },
    {
      "row_index": 5,
      "col_index": 3,
      "bbox": {
        "x0": 0,
        "y0": 0,
        "x1": 0,
        "y1": 0
      },
      "cell_type": "number",
      "raw_value": "0.795",
      "normalized_value": 0.795,
      "rowspan": 1,
      "colspan": 1,
      "formula_text": null,
      "units": null
    },
    {
      "row_index": 5,
      "col_index": 4,
      "bbox": {
        "x0": 0,
        "y0": 0,
        "x1": 0,
        "y1": 0
      },
      "cell_type": "blank",
      "raw_value": "",
      "normalized_value": "",
      "rowspan": 1,
      "colspan": 1,
      "formula_text": null,
      "units": null
    },
    {
      "row_index": 5,
      "col_index": 5,
      "bbox": {
        "x0": 0,
        "y0": 0,
        "x1": 0,
        "y1": 0
      },
      "cell_type": "number",
      "raw_value": "0.952",
      "normalized_value": 0.952,
      "rowspan": 1,
      "colspan": 1,
      "formula_text": null,
      "units": null
    },
    {
      "row_index": 5,
      "col_index": 6,
      "bbox": {
        "x0": 0,
        "y0": 0,
        "x1": 0,
        "y1": 0
      },
      "cell_type": "blank",
      "raw_value": "",
      "normalized_value": "",
      "rowspan": 1,
      "colspan": 1,
      "formula_text": null,
      "units": null
    },
    {
      "row_index": 5,
      "col_index": 7,
      "bbox": {
        "x0": 0,
        "y0": 0,
        "x1": 0,
        "y1": 0
      },
      "cell_type": "number",
      "raw_value": "0.024",
      "normalized_value": 0.024,
      "rowspan": 1,
      "colspan": 1,
      "formula_text": null,
      "units": null
    },
    {
      "row_index": 5,
      "col_index": 8,
      "bbox": {
        "x0": 0,
        "y0": 0,
        "x1": 0,
        "y1": 0
      },
      "cell_type": "blank",
      "raw_value": "",
      "normalized_value": "",
      "rowspan": 1,
      "colspan": 1,
      "formula_text": null,
      "units": null
    },
    {
      "row_index": 5,
      "col_index": 9,
      "bbox": {
        "x0": 0,
        "y0": 0,
        "x1": 0,
        "y1": 0
      },
      "cell_type": "number",
      "raw_value": "0.022",
      "normalized_value": 0.022,
      "rowspan": 1,
      "colspan": 1,
      "formula_text": null,
      "units": null
    },
    {
      "row_index": 5,
      "col_index": 10,
      "bbox": {
        "x0": 0,
        "y0": 0,
        "x1": 0,
        "y1": 0
      },
      "cell_type": "blank",
      "raw_value": "",
      "normalized_value": "",
      "rowspan": 1,
      "colspan": 1,
      "formula_text": null,
      "units": null
    },
    {
      "row_index": 6,
      "col_index": 0,
      "bbox": {
        "x0": 0,
        "y0": 0,
        "x1": 0,
        "y1": 0
      },
      "cell_type": "blank",
      "raw_value": "",
      "normalized_value": "",
      "rowspan": 1,
      "colspan": 1,
      "formula_text": null,
      "units": null
    },
    {
      "row_index": 6,
      "col_index": 1,
      "bbox": {
        "x0": 0,
        "y0": 0,
        "x1": 0,
        "y1": 0
      },
      "cell_type": "text",
      "raw_value": "Hong Kong (Hang Seng)",
      "normalized_value": "Hong Kong (Hang Seng)",
      "rowspan": 1,
      "colspan": 1,
      "formula_text": null,
      "units": null
    },
    {
      "row_index": 6,
      "col_index": 2,
      "bbox": {
        "x0": 0,
        "y0": 0,
        "x1": 0,
        "y1": 0
      },
      "cell_type": "blank",
      "raw_value": "",
      "normalized_value": "",
      "rowspan": 1,
      "colspan": 1,
      "formula_text": null,
      "units": null
    },
    {
      "row_index": 6,
      "col_index": 3,
      "bbox": {
        "x0": 0,
        "y0": 0,
        "x1": 0,
        "y1": 0
      },
      "cell_type": "number",
      "raw_value": "0.895",
      "normalized_value": 0.895,
      "rowspan": 1,
      "colspan": 1,
      "formula_text": null,
      "units": null
    },
    {
      "row_index": 6,
      "col_index": 4,
      "bbox": {
        "x0": 0,
        "y0": 0,
        "x1": 0,
        "y1": 0
      },
      "cell_type": "blank",
      "raw_value": "",
      "normalized_value": "",
      "rowspan": 1,
      "colspan": 1,
      "formula_text": null,
      "units": null
    },
    {
      "row_index": 6,
      "col_index": 5,
      "bbox": {
        "x0": 0,
        "y0": 0,
        "x1": 0,
        "y1": 0
      },
      "cell_type": "number",
      "raw_value": "0.707",
      "normalized_value": 0.707,
      "rowspan": 1,
      "colspan": 1,
      "formula_text": null,
      "units": null
    },
    {
      "row_index": 6,
      "col_index": 6,
      "bbox": {
        "x0": 0,
        "y0": 0,
        "x1": 0,
        "y1": 0
      },
      "cell_type": "blank",
      "raw_value": "",
      "normalized_value": "",
      "rowspan": 1,
      "colspan": 1,
      "formula_text": null,
      "units": null
    },
    {
      "row_index": 6,
      "col_index": 7,
      "bbox": {
        "x0": 0,
        "y0": 0,
        "x1": 0,
        "y1": 0
      },
      "cell_type": "number",
      "raw_value": "0.033",
      "normalized_value": 0.033,
      "rowspan": 1,
      "colspan": 1,
      "formula_text": null,
      "units": null
    },
    {
      "row_index": 6,
      "col_index": 8,
      "bbox": {
        "x0": 0,
        "y0": 0,
        "x1": 0,
        "y1": 0
      },
      "cell_type": "blank",
      "raw_value": "",
      "normalized_value": "",
      "rowspan": 1,
      "colspan": 1,
      "formula_text": null,
      "units": null
    },
    {
      "row_index": 6,
      "col_index": 9,
      "bbox": {
        "x0": 0,
        "y0": 0,
        "x1": 0,
        "y1": 0
      },
      "cell_type": "number",
      "raw_value": "0.037",
      "normalized_value": 0.037,
      "rowspan": 1,
      "colspan": 1,
      "formula_text": null,
      "units": null
    },
    {
      "row_index": 6,
      "col_index": 10,
      "bbox": {
        "x0": 0,
        "y0": 0,
        "x1": 0,
        "y1": 0
      },
      "cell_type": "blank",
      "raw_value": "",
      "normalized_value": "",
      "rowspan": 1,
      "colspan": 1,
      "formula_text": null,
      "units": null
    },
    {
      "row_index": 7,
      "col_index": 0,
      "bbox": {
        "x0": 0,
        "y0": 0,
        "x1": 0,
        "y1": 0
      },
      "cell_type": "blank",
      "raw_value": "",
      "normalized_value": "",
      "rowspan": 1,
      "colspan": 1,
      "formula_text": null,
      "units": null
    },
    {
      "row_index": 7,
      "col_index": 1,
      "bbox": {
        "x0": 0,
        "y0": 0,
        "x1": 0,
        "y1": 0
      },
      "cell_type": "text",
      "raw_value": "India (BSE)",
      "normalized_value": "India (BSE)",
      "rowspan": 1,
      "colspan": 1,
      "formula_text": null,
      "units": null
    },
    {
      "row_index": 7,
      "col_index": 2,
      "bbox": {
        "x0": 0,
        "y0": 0,
        "x1": 0,
        "y1": 0
      },
      "cell_type": "blank",
      "raw_value": "",
      "normalized_value": "",
      "rowspan": 1,
      "colspan": 1,
      "formula_text": null,
      "units": null
    },
    {
      "row_index": 7,
      "col_index": 3,
      "bbox": {
        "x0": 0,
        "y0": 0,
        "x1": 0,
        "y1": 0
      },
      "cell_type": "number",
      "raw_value": "0.927",
      "normalized_value": 0.927,
      "rowspan": 1,
      "colspan": 1,
      "formula_text": null,
      "units": null
    },
    {
      "row_index": 7,
      "col_index": 4,
      "bbox": {
        "x0": 0,
        "y0": 0,
        "x1": 0,
        "y1": 0
      },
      "cell_type": "blank",
      "raw_value": "",
      "normalized_value": "",
      "rowspan": 1,
      "colspan": 1,
      "formula_text": null,
      "units": null
    },
    {
      "row_index": 7,
      "col_index": 5,
      "bbox": {
        "x0": 0,
        "y0": 0,
        "x1": 0,
        "y1": 0
      },
      "cell_type": "number",
      "raw_value": "0.902",
      "normalized_value": 0.902,
      "rowspan": 1,
      "colspan": 1,
      "formula_text": null,
      "units": null
    },
    {
      "row_index": 7,
      "col_index": 6,
      "bbox": {
        "x0": 0,
        "y0": 0,
        "x1": 0,
        "y1": 0
      },
      "cell_type": "blank",
      "raw_value": "",
      "normalized_value": "",
      "rowspan": 1,
      "colspan": 1,
      "formula_text": null,
      "units": null
    },
    {
      "row_index": 7,
      "col_index": 7,
      "bbox": {
        "x0": 0,
        "y0": 0,
        "x1": 0,
        "y1": 0
      },
      "cell_type": "number",
      "raw_value": "0.040",
      "normalized_value": 0.04,
      "rowspan": 1,
      "colspan": 1,
      "formula_text": null,
      "units": null
    },
    {
      "row_index": 7,
      "col_index": 8,
      "bbox": {
        "x0": 0,
        "y0": 0,
        "x1": 0,
        "y1": 0
      },
      "cell_type": "blank",
      "raw_value": "",
      "normalized_value": "",
      "rowspan": 1,
      "colspan": 1,
      "formula_text": null,
      "units": null
    },
    {
      "row_index": 7,
      "col_index": 9,
      "bbox": {
        "x0": 0,
        "y0": 0,
        "x1": 0,
        "y1": 0
      },
      "cell_type": "number",
      "raw_value": "0.049",
      "normalized_value": 0.049,
      "rowspan": 1,
      "colspan": 1,
      "formula_text": null,
      "units": null
    },
    {
      "row_index": 7,
      "col_index": 10,
      "bbox": {
        "x0": 0,
        "y0": 0,
        "x1": 0,
        "y1": 0
      },
      "cell_type": "blank",
      "raw_value": "",
      "normalized_value": "",
      "rowspan": 1,
      "colspan": 1,
      "formula_text": null,
      "units": null
    },
    {
      "row_index": 8,
      "col_index": 0,
      "bbox": {
        "x0": 0,
        "y0": 0,
        "x1": 0,
        "y1": 0
      },
      "cell_type": "blank",
      "raw_value": "",
      "normalized_value": "",
      "rowspan": 1,
      "colspan": 1,
      "formula_text": null,
      "units": null
    },
    {
      "row_index": 8,
      "col_index": 1,
      "bbox": {
        "x0": 0,
        "y0": 0,
        "x1": 0,
        "y1": 0
      },
      "cell_type": "text",
      "raw_value": "Japan (Nikkei)",
      "normalized_value": "Japan (Nikkei)",
      "rowspan": 1,
      "colspan": 1,
      "formula_text": null,
      "units": null
    },
    {
      "row_index": 8,
      "col_index": 2,
      "bbox": {
        "x0": 0,
        "y0": 0,
        "x1": 0,
        "y1": 0
      },
      "cell_type": "blank",
      "raw_value": "",
      "normalized_value": "",
      "rowspan": 1,
      "colspan": 1,
      "formula_text": null,
      "units": null
    },
    {
      "row_index": 8,
      "col_index": 3,
      "bbox": {
        "x0": 0,
        "y0": 0,
        "x1": 0,
        "y1": 0
      },
      "cell_type": "number",
      "raw_value": "0.952",
      "normalized_value": 0.952,
      "rowspan": 1,
      "colspan": 1,
      "formula_text": null,
      "units": null
    },
    {
      "row_index": 8,
      "col_index": 4,
      "bbox": {
        "x0": 0,
        "y0": 0,
        "x1": 0,
        "y1": 0
      },
      "cell_type": "blank",
      "raw_value": "",
      "normalized_value": "",
      "rowspan": 1,
      "colspan": 1,
      "formula_text": null,
      "units": null
    },
    {
      "row_index": 8,
      "col_index": 5,
      "bbox": {
        "x0": 0,
        "y0": 0,
        "x1": 0,
        "y1": 0
      },
      "cell_type": "number",
      "raw_value": "0.748",
      "normalized_value": 0.748,
      "rowspan": 1,
      "colspan": 1,
      "formula_text": null,
      "units": null
    },
    {
      "row_index": 8,
      "col_index": 6,
      "bbox": {
        "x0": 0,
        "y0": 0,
        "x1": 0,
        "y1": 0
      },
      "cell_type": "blank",
      "raw_value": "",
      "normalized_value": "",
      "rowspan": 1,
      "colspan": 1,
      "formula_text": null,
      "units": null
    },
    {
      "row_index": 8,
      "col_index": 7,
      "bbox": {
        "x0": 0,
        "y0": 0,
        "x1": 0,
        "y1": 0
      },
      "cell_type": "number",
      "raw_value": "0.028",
      "normalized_value": 0.028,
      "rowspan": 1,
      "colspan": 1,
      "formula_text": null,
      "units": null
    },
    {
      "row_index": 8,
      "col_index": 8,
      "bbox": {
        "x0": 0,
        "y0": 0,
        "x1": 0,
        "y1": 0
      },
      "cell_type": "blank",
      "raw_value": "",
      "normalized_value": "",
      "rowspan": 1,
      "colspan": 1,
      "formula_text": null,
      "units": null
    },
    {
      "row_index": 8,
      "col_index": 9,
      "bbox": {
        "x0": 0,
        "y0": 0,
        "x1": 0,
        "y1": 0
      },
      "cell_type": "number",
      "raw_value": "0.026",
      "normalized_value": 0.026,
      "rowspan": 1,
      "colspan": 1,
      "formula_text": null,
      "units": null
    },
    {
      "row_index": 8,
      "col_index": 10,
      "bbox": {
        "x0": 0,
        "y0": 0,
        "x1": 0,
        "y1": 0
      },
      "cell_type": "blank",
      "raw_value": "",
      "normalized_value": "",
      "rowspan": 1,
      "colspan": 1,
      "formula_text": null,
      "units": null
    },
    {
      "row_index": 9,
      "col_index": 0,
      "bbox": {
        "x0": 0,
        "y0": 0,
        "x1": 0,
        "y1": 0
      },
      "cell_type": "blank",
      "raw_value": "",
      "normalized_value": "",
      "rowspan": 1,
      "colspan": 1,
      "formula_text": null,
      "units": null
    },
    {
      "row_index": 9,
      "col_index": 1,
      "bbox": {
        "x0": 0,
        "y0": 0,
        "x1": 0,
        "y1": 0
      },
      "cell_type": "text",
      "raw_value": "Korea (KOSPI)",
      "normalized_value": "Korea (KOSPI)",
      "rowspan": 1,
      "colspan": 1,
      "formula_text": null,
      "units": null
    },
    {
      "row_index": 9,
      "col_index": 2,
      "bbox": {
        "x0": 0,
        "y0": 0,
        "x1": 0,
        "y1": 0
      },
      "cell_type": "blank",
      "raw_value": "",
      "normalized_value": "",
      "rowspan": 1,
      "colspan": 1,
      "formula_text": null,
      "units": null
    },
    {
      "row_index": 9,
      "col_index": 3,
      "bbox": {
        "x0": 0,
        "y0": 0,
        "x1": 0,
        "y1": 0
      },
      "cell_type": "number",
      "raw_value": "1.032",
      "normalized_value": 1.032,
      "rowspan": 1,
      "colspan": 1,
      "formula_text": null,
      "units": null
    },
    {
      "row_index": 9,
      "col_index": 4,
      "bbox": {
        "x0": 0,
        "y0": 0,
        "x1": 0,
        "y1": 0
      },
      "cell_type": "blank",
      "raw_value": "",
      "normalized_value": "",
      "rowspan": 1,
      "colspan": 1,
      "formula_text": null,
      "units": null
    },
    {
      "row_index": 9,
      "col_index": 5,
      "bbox": {
        "x0": 0,
        "y0": 0,
        "x1": 0,
        "y1": 0
      },
      "cell_type": "number",
      "raw_value": "1.024",
      "normalized_value": 1.024,
      "rowspan": 1,
      "colspan": 1,
      "formula_text": null,
      "units": null
    },
    {
      "row_index": 9,
      "col_index": 6,
      "bbox": {
        "x0": 0,
        "y0": 0,
        "x1": 0,
        "y1": 0
      },
      "cell_type": "blank",
      "raw_value": "",
      "normalized_value": "",
      "rowspan": 1,
      "colspan": 1,
      "formula_text": null,
      "units": null
    },
    {
      "row_index": 9,
      "col_index": 7,
      "bbox": {
        "x0": 0,
        "y0": 0,
        "x1": 0,
        "y1": 0
      },
      "cell_type": "number",
      "raw_value": "0.030",
      "normalized_value": 0.03,
      "rowspan": 1,
      "colspan": 1,
      "formula_text": null,
      "units": null
    },
    {
      "row_index": 9,
      "col_index": 8,
      "bbox": {
        "x0": 0,
        "y0": 0,
        "x1": 0,
        "y1": 0
      },
      "cell_type": "blank",
      "raw_value": "",
      "normalized_value": "",
      "rowspan": 1,
      "colspan": 1,
      "formula_text": null,
      "units": null
    },
    {
      "row_index": 9,
      "col_index": 9,
      "bbox": {
        "x0": 0,
        "y0": 0,
        "x1": 0,
        "y1": 0
      },
      "cell_type": "number",
      "raw_value": "0.039",
      "normalized_value": 0.039,
      "rowspan": 1,
      "colspan": 1,
      "formula_text": null,
      "units": null
    },
    {
      "row_index": 9,
      "col_index": 10,
      "bbox": {
        "x0": 0,
        "y0": 0,
        "x1": 0,
        "y1": 0
      },
      "cell_type": "blank",
      "raw_value": "",
      "normalized_value": "",
      "rowspan": 1,
      "colspan": 1,
      "formula_text": null,
      "units": null
    },
    {
      "row_index": 10,
      "col_index": 0,
      "bbox": {
        "x0": 0,
        "y0": 0,
        "x1": 0,
        "y1": 0
      },
      "cell_type": "blank",
      "raw_value": "",
      "normalized_value": "",
      "rowspan": 1,
      "colspan": 1,
      "formula_text": null,
      "units": null
    },
    {
      "row_index": 10,
      "col_index": 1,
      "bbox": {
        "x0": 0,
        "y0": 0,
        "x1": 0,
        "y1": 0
      },
      "cell_type": "text",
      "raw_value": "Swiss (SMI)",
      "normalized_value": "Swiss (SMI)",
      "rowspan": 1,
      "colspan": 1,
      "formula_text": null,
      "units": null
    },
    {
      "row_index": 10,
      "col_index": 2,
      "bbox": {
        "x0": 0,
        "y0": 0,
        "x1": 0,
        "y1": 0
      },
      "cell_type": "blank",
      "raw_value": "",
      "normalized_value": "",
      "rowspan": 1,
      "colspan": 1,
      "formula_text": null,
      "units": null
    },
    {
      "row_index": 10,
      "col_index": 3,
      "bbox": {
        "x0": 0,
        "y0": 0,
        "x1": 0,
        "y1": 0
      },
      "cell_type": "number",
      "raw_value": "0.637",
      "normalized_value": 0.637,
      "rowspan": 1,
      "colspan": 1,
      "formula_text": null,
      "units": null
    },
    {
      "row_index": 10,
      "col_index": 4,
      "bbox": {
        "x0": 0,
        "y0": 0,
        "x1": 0,
        "y1": 0
      },
      "cell_type": "blank",
      "raw_value": "",
      "normalized_value": "",
      "rowspan": 1,
      "colspan": 1,
      "formula_text": null,
      "units": null
    },
    {
      "row_index": 10,
      "col_index": 5,
      "bbox": {
        "x0": 0,
        "y0": 0,
        "x1": 0,
        "y1": 0
      },
      "cell_type": "number",
      "raw_value": "0.627",
      "normalized_value": 0.627,
      "rowspan": 1,
      "colspan": 1,
      "formula_text": null,
      "units": null
    },
    {
      "row_index": 10,
      "col_index": 6,
      "bbox": {
        "x0": 0,
        "y0": 0,
        "x1": 0,
        "y1": 0
      },
      "cell_type": "blank",
      "raw_value": "",
      "normalized_value": "",
      "rowspan": 1,
      "colspan": 1,
      "formula_text": null,
      "units": null
    },
    {
      "row_index": 10,
      "col_index": 7,
      "bbox": {
        "x0": 0,
        "y0": 0,
        "x1": 0,
        "y1": 0
      },
      "cell_type": "number",
      "raw_value": "0.022",
      "normalized_value": 0.022,
      "rowspan": 1,
      "colspan": 1,
      "formula_text": null,
      "units": null
    },
    {
      "row_index": 10,
      "col_index": 8,
      "bbox": {
        "x0": 0,
        "y0": 0,
        "x1": 0,
        "y1": 0
      },
      "cell_type": "blank",
      "raw_value": "",
      "normalized_value": "",
      "rowspan": 1,
      "colspan": 1,
      "formula_text": null,
      "units": null
    },
    {
      "row_index": 10,
      "col_index": 9,
      "bbox": {
        "x0": 0,
        "y0": 0,
        "x1": 0,
        "y1": 0
      },
      "cell_type": "number",
      "raw_value": "0.023",
      "normalized_value": 0.023,
      "rowspan": 1,
      "colspan": 1,
      "formula_text": null,
      "units": null
    },
    {
      "row_index": 10,
      "col_index": 10,
      "bbox": {
        "x0": 0,
        "y0": 0,
        "x1": 0,
        "y1": 0
      },
      "cell_type": "blank",
      "raw_value": "",
      "normalized_value": "",
      "rowspan": 1,
      "colspan": 1,
      "formula_text": null,
      "units": null
    },
    {
      "row_index": 11,
      "col_index": 0,
      "bbox": {
        "x0": 0,
        "y0": 0,
        "x1": 0,
        "y1": 0
      },
      "cell_type": "blank",
      "raw_value": "",
      "normalized_value": "",
      "rowspan": 1,
      "colspan": 1,
      "formula_text": null,
      "units": null
    },
    {
      "row_index": 11,
      "col_index": 1,
      "bbox": {
        "x0": 0,
        "y0": 0,
        "x1": 0,
        "y1": 0
      },
      "cell_type": "text",
      "raw_value": "Canada (TSX)",
      "normalized_value": "Canada (TSX)",
      "rowspan": 1,
      "colspan": 1,
      "formula_text": null,
      "units": null
    },
    {
      "row_index": 11,
      "col_index": 2,
      "bbox": {
        "x0": 0,
        "y0": 0,
        "x1": 0,
        "y1": 0
      },
      "cell_type": "blank",
      "raw_value": "",
      "normalized_value": "",
      "rowspan": 1,
      "colspan": 1,
      "formula_text": null,
      "units": null
    },
    {
      "row_index": 11,
      "col_index": 3,
      "bbox": {
        "x0": 0,
        "y0": 0,
        "x1": 0,
        "y1": 0
      },
      "cell_type": "number",
      "raw_value": "1.205",
      "normalized_value": 1.205,
      "rowspan": 1,
      "colspan": 1,
      "formula_text": null,
      "units": null
    },
    {
      "row_index": 11,
      "col_index": 4,
      "bbox": {
        "x0": 0,
        "y0": 0,
        "x1": 0,
        "y1": 0
      },
      "cell_type": "blank",
      "raw_value": "",
      "normalized_value": "",
      "rowspan": 1,
      "colspan": 1,
      "formula_text": null,
      "units": null
    },
    {
      "row_index": 11,
      "col_index": 5,
      "bbox": {
        "x0": 0,
        "y0": 0,
        "x1": 0,
        "y1": 0
      },
      "cell_type": "number",
      "raw_value": "1.030",
      "normalized_value": 1.03,
      "rowspan": 1,
      "colspan": 1,
      "formula_text": null,
      "units": null
    },
    {
      "row_index": 11,
      "col_index": 6,
      "bbox": {
        "x0": 0,
        "y0": 0,
        "x1": 0,
        "y1": 0
      },
      "cell_type": "blank",
      "raw_value": "",
      "normalized_value": "",
      "rowspan": 1,
      "colspan": 1,
      "formula_text": null,
      "units": null
    },
    {
      "row_index": 11,
      "col_index": 7,
      "bbox": {
        "x0": 0,
        "y0": 0,
        "x1": 0,
        "y1": 0
      },
      "cell_type": "number",
      "raw_value": "0.022",
      "normalized_value": 0.022,
      "rowspan": 1,
      "colspan": 1,
      "formula_text": null,
      "units": null
    },
    {
      "row_index": 11,
      "col_index": 8,
      "bbox": {
        "x0": 0,
        "y0": 0,
        "x1": 0,
        "y1": 0
      },
      "cell_type": "blank",
      "raw_value": "",
      "normalized_value": "",
      "rowspan": 1,
      "colspan": 1,
      "formula_text": null,
      "units": null
    },
    {
      "row_index": 11,
      "col_index": 9,
      "bbox": {
        "x0": 0,
        "y0": 0,
        "x1": 0,
        "y1": 0
      },
      "cell_type": "number",
      "raw_value": "0.020",
      "normalized_value": 0.02,
      "rowspan": 1,
      "colspan": 1,
      "formula_text": null,
      "units": null
    },
    {
      "row_index": 11,
      "col_index": 10,
      "bbox": {
        "x0": 0,
        "y0": 0,
        "x1": 0,
        "y1": 0
      },
      "cell_type": "blank",
      "raw_value": "",
      "normalized_value": "",
      "rowspan": 1,
      "colspan": 1,
      "formula_text": null,
      "units": null
    },
    {
      "row_index": 12,
      "col_index": 0,
      "bbox": {
        "x0": 0,
        "y0": 0,
        "x1": 0,
        "y1": 0
      },
      "cell_type": "blank",
      "raw_value": "",
      "normalized_value": "",
      "rowspan": 1,
      "colspan": 1,
      "formula_text": null,
      "units": null
    },
    {
      "row_index": 12,
      "col_index": 1,
      "bbox": {
        "x0": 0,
        "y0": 0,
        "x1": 0,
        "y1": 0
      },
      "cell_type": "text",
      "raw_value": "MSCI-Arabian",
      "normalized_value": "MSCI-Arabian",
      "rowspan": 1,
      "colspan": 1,
      "formula_text": null,
      "units": null
    },
    {
      "row_index": 12,
      "col_index": 2,
      "bbox": {
        "x0": 0,
        "y0": 0,
        "x1": 0,
        "y1": 0
      },
      "cell_type": "blank",
      "raw_value": "",
      "normalized_value": "",
      "rowspan": 1,
      "colspan": 1,
      "formula_text": null,
      "units": null
    },
    {
      "row_index": 12,
      "col_index": 3,
      "bbox": {
        "x0": 0,
        "y0": 0,
        "x1": 0,
        "y1": 0
      },
      "cell_type": "number",
      "raw_value": "0.640",
      "normalized_value": 0.64,
      "rowspan": 1,
      "colspan": 1,
      "formula_text": null,
      "units": null
    },
    {
      "row_index": 12,
      "col_index": 4,
      "bbox": {
        "x0": 0,
        "y0": 0,
        "x1": 0,
        "y1": 0
      },
      "cell_type": "blank",
      "raw_value": "",
      "normalized_value": "",
      "rowspan": 1,
      "colspan": 1,
      "formula_text": null,
      "units": null
    },
    {
      "row_index": 12,
      "col_index": 5,
      "bbox": {
        "x0": 0,
        "y0": 0,
        "x1": 0,
        "y1": 0
      },
      "cell_type": "blank",
      "raw_value": "",
      "normalized_value": "",
      "rowspan": 1,
      "colspan": 1,
      "formula_text": null,
      "units": null
    },
    {
      "row_index": 12,
      "col_index": 6,
      "bbox": {
        "x0": 0,
        "y0": 0,
        "x1": 0,
        "y1": 0
      },
      "cell_type": "blank",
      "raw_value": "",
      "normalized_value": "",
      "rowspan": 1,
      "colspan": 1,
      "formula_text": null,
      "units": null
    },
    {
      "row_index": 12,
      "col_index": 7,
      "bbox": {
        "x0": 0,
        "y0": 0,
        "x1": 0,
        "y1": 0
      },
      "cell_type": "number",
      "raw_value": "0.136",
      "normalized_value": 0.136,
      "rowspan": 1,
      "colspan": 1,
      "formula_text": null,
      "units": null
    },
    {
      "row_index": 12,
      "col_index": 8,
      "bbox": {
        "x0": 0,
        "y0": 0,
        "x1": 0,
        "y1": 0
      },
      "cell_type": "blank",
      "raw_value": "",
      "normalized_value": "",
      "rowspan": 1,
      "colspan": 1,
      "formula_text": null,
      "units": null
    },
    {
      "row_index": 12,
      "col_index": 9,
      "bbox": {
        "x0": 0,
        "y0": 0,
        "x1": 0,
        "y1": 0
      },
      "cell_type": "blank",
      "raw_value": "",
      "normalized_value": "",
      "rowspan": 1,
      "colspan": 1,
      "formula_text": null,
      "units": null
    },
    {
      "row_index": 12,
      "col_index": 10,
      "bbox": {
        "x0": 0,
        "y0": 0,
        "x1": 0,
        "y1": 0
      },
      "cell_type": "blank",
      "raw_value": "",
      "normalized_value": "",
      "rowspan": 1,
      "colspan": 1,
      "formula_text": null,
      "units": null
    },
    {
      "row_index": 13,
      "col_index": 0,
      "bbox": {
        "x0": 0,
        "y0": 0,
        "x1": 0,
        "y1": 0
      },
      "cell_type": "blank",
      "raw_value": "",
      "normalized_value": "",
      "rowspan": 1,
      "colspan": 1,
      "formula_text": null,
      "units": null
    },
    {
      "row_index": 13,
      "col_index": 1,
      "bbox": {
        "x0": 0,
        "y0": 0,
        "x1": 0,
        "y1": 0
      },
      "cell_type": "text",
      "raw_value": "MSCI-Latin Amer",
      "normalized_value": "MSCI-Latin Amer",
      "rowspan": 1,
      "colspan": 1,
      "formula_text": null,
      "units": null
    },
    {
      "row_index": 13,
      "col_index": 2,
      "bbox": {
        "x0": 0,
        "y0": 0,
        "x1": 0,
        "y1": 0
      },
      "cell_type": "blank",
      "raw_value": "",
      "normalized_value": "",
      "rowspan": 1,
      "colspan": 1,
      "formula_text": null,
      "units": null
    },
    {
      "row_index": 13,
      "col_index": 3,
      "bbox": {
        "x0": 0,
        "y0": 0,
        "x1": 0,
        "y1": 0
      },
      "cell_type": "number",
      "raw_value": "1.323",
      "normalized_value": 1.323,
      "rowspan": 1,
      "colspan": 1,
      "formula_text": null,
      "units": null
    },
    {
      "row_index": 13,
      "col_index": 4,
      "bbox": {
        "x0": 0,
        "y0": 0,
        "x1": 0,
        "y1": 0
      },
      "cell_type": "blank",
      "raw_value": "",
      "normalized_value": "",
      "rowspan": 1,
      "colspan": 1,
      "formula_text": null,
      "units": null
    },
    {
      "row_index": 13,
      "col_index": 5,
      "bbox": {
        "x0": 0,
        "y0": 0,
        "x1": 0,
        "y1": 0
      },
      "cell_type": "blank",
      "raw_value": "",
      "normalized_value": "",
      "rowspan": 1,
      "colspan": 1,
      "formula_text": null,
      "units": null
    },
    {
      "row_index": 13,
      "col_index": 6,
      "bbox": {
        "x0": 0,
        "y0": 0,
        "x1": 0,
        "y1": 0
      },
      "cell_type": "blank",
      "raw_value": "",
      "normalized_value": "",
      "rowspan": 1,
      "colspan": 1,
      "formula_text": null,
      "units": null
    },
    {
      "row_index": 13,
      "col_index": 7,
      "bbox": {
        "x0": 0,
        "y0": 0,
        "x1": 0,
        "y1": 0
      },
      "cell_type": "number",
      "raw_value": "0.146",
      "normalized_value": 0.146,
      "rowspan": 1,
      "colspan": 1,
      "formula_text": null,
      "units": null
    },
    {
      "row_index": 13,
      "col_index": 8,
      "bbox": {
        "x0": 0,
        "y0": 0,
        "x1": 0,
        "y1": 0
      },
      "cell_type": "blank",
      "raw_value": "",
      "normalized_value": "",
      "rowspan": 1,
      "colspan": 1,
      "formula_text": null,
      "units": null
    },
    {
      "row_index": 13,
      "col_index": 9,
      "bbox": {
        "x0": 0,
        "y0": 0,
        "x1": 0,
        "y1": 0
      },
      "cell_type": "blank",
      "raw_value": "",
      "normalized_value": "",
      "rowspan": 1,
      "colspan": 1,
      "formula_text": null,
      "units": null
    },
    {
      "row_index": 13,
      "col_index": 10,
      "bbox": {
        "x0": 0,
        "y0": 0,
        "x1": 0,
        "y1": 0
      },
      "cell_type": "blank",
      "raw_value": "",
      "normalized_value": "",
      "rowspan": 1,
      "colspan": 1,
      "formula_text": null,
      "units": null
    },
    {
      "row_index": 14,
      "col_index": 0,
      "bbox": {
        "x0": 0,
        "y0": 0,
        "x1": 0,
        "y1": 0
      },
      "cell_type": "blank",
      "raw_value": "",
      "normalized_value": "",
      "rowspan": 1,
      "colspan": 1,
      "formula_text": null,
      "units": null
    },
    {
      "row_index": 14,
      "col_index": 1,
      "bbox": {
        "x0": 0,
        "y0": 0,
        "x1": 0,
        "y1": 0
      },
      "cell_type": "text",
      "raw_value": "MSCI-World",
      "normalized_value": "MSCI-World",
      "rowspan": 1,
      "colspan": 1,
      "formula_text": null,
      "units": null
    },
    {
      "row_index": 14,
      "col_index": 2,
      "bbox": {
        "x0": 0,
        "y0": 0,
        "x1": 0,
        "y1": 0
      },
      "cell_type": "blank",
      "raw_value": "",
      "normalized_value": "",
      "rowspan": 1,
      "colspan": 1,
      "formula_text": null,
      "units": null
    },
    {
      "row_index": 14,
      "col_index": 3,
      "bbox": {
        "x0": 0,
        "y0": 0,
        "x1": 0,
        "y1": 0
      },
      "cell_type": "number",
      "raw_value": "1.000",
      "normalized_value": 1.0,
      "rowspan": 1,
      "colspan": 1,
      "formula_text": null,
      "units": null
    },
    {
      "row_index": 14,
      "col_index": 4,
      "bbox": {
        "x0": 0,
        "y0": 0,
        "x1": 0,
        "y1": 0
      },
      "cell_type": "blank",
      "raw_value": "",
      "normalized_value": "",
      "rowspan": 1,
      "colspan": 1,
      "formula_text": null,
      "units": null
    },
    {
      "row_index": 14,
      "col_index": 5,
      "bbox": {
        "x0": 0,
        "y0": 0,
        "x1": 0,
        "y1": 0
      },
      "cell_type": "blank",
      "raw_value": "",
      "normalized_value": "",
      "rowspan": 1,
      "colspan": 1,
      "formula_text": null,
      "units": null
    },
    {
      "row_index": 14,
      "col_index": 6,
      "bbox": {
        "x0": 0,
        "y0": 0,
        "x1": 0,
        "y1": 0
      },
      "cell_type": "blank",
      "raw_value": "",
      "normalized_value": "",
      "rowspan": 1,
      "colspan": 1,
      "formula_text": null,
      "units": null
    },
    {
      "row_index": 14,
      "col_index": 7,
      "bbox": {
        "x0": 0,
        "y0": 0,
        "x1": 0,
        "y1": 0
      },
      "cell_type": "number",
      "raw_value": "0.000",
      "normalized_value": 0.0,
      "rowspan": 1,
      "colspan": 1,
      "formula_text": null,
      "units": null
    },
    {
      "row_index": 14,
      "col_index": 8,
      "bbox": {
        "x0": 0,
        "y0": 0,
        "x1": 0,
        "y1": 0
      },
      "cell_type": "blank",
      "raw_value": "",
      "normalized_value": "",
      "rowspan": 1,
      "colspan": 1,
      "formula_text": null,
      "units": null
    },
    {
      "row_index": 14,
      "col_index": 9,
      "bbox": {
        "x0": 0,
        "y0": 0,
        "x1": 0,
        "y1": 0
      },
      "cell_type": "blank",
      "raw_value": "",
      "normalized_value": "",
      "rowspan": 1,
      "colspan": 1,
      "formula_text": null,
      "units": null
    },
    {
      "row_index": 14,
      "col_index": 10,
      "bbox": {
        "x0": 0,
        "y0": 0,
        "x1": 0,
        "y1": 0
      },
      "cell_type": "blank",
      "raw_value": "",
      "normalized_value": "",
      "rowspan": 1,
      "colspan": 1,
      "formula_text": null,
      "units": null
    },
    {
      "row_index": 15,
      "col_index": 0,
      "bbox": {
        "x0": 0,
        "y0": 0,
        "x1": 0,
        "y1": 0
      },
      "cell_type": "blank",
      "raw_value": "",
      "normalized_value": "",
      "rowspan": 1,
      "colspan": 1,
      "formula_text": null,
      "units": null
    },
    {
      "row_index": 15,
      "col_index": 1,
      "bbox": {
        "x0": 0,
        "y0": 0,
        "x1": 0,
        "y1": 0
      },
      "cell_type": "text",
      "raw_value": "Mean",
      "normalized_value": "Mean",
      "rowspan": 1,
      "colspan": 1,
      "formula_text": null,
      "units": null
    },
    {
      "row_index": 15,
      "col_index": 2,
      "bbox": {
        "x0": 0,
        "y0": 0,
        "x1": 0,
        "y1": 0
      },
      "cell_type": "blank",
      "raw_value": "",
      "normalized_value": "",
      "rowspan": 1,
      "colspan": 1,
      "formula_text": null,
      "units": null
    },
    {
      "row_index": 15,
      "col_index": 3,
      "bbox": {
        "x0": 0,
        "y0": 0,
        "x1": 0,
        "y1": 0
      },
      "cell_type": "number",
      "raw_value": "0.930",
      "normalized_value": 0.93,
      "rowspan": 1,
      "colspan": 1,
      "formula_text": null,
      "units": null
    },
    {
      "row_index": 15,
      "col_index": 4,
      "bbox": {
        "x0": 0,
        "y0": 0,
        "x1": 0,
        "y1": 0
      },
      "cell_type": "blank",
      "raw_value": "",
      "normalized_value": "",
      "rowspan": 1,
      "colspan": 1,
      "formula_text": null,
      "units": null
    },
    {
      "row_index": 15,
      "col_index": 5,
      "bbox": {
        "x0": 0,
        "y0": 0,
        "x1": 0,
        "y1": 0
      },
      "cell_type": "number",
      "raw_value": "0.863",
      "normalized_value": 0.863,
      "rowspan": 1,
      "colspan": 1,
      "formula_text": null,
      "units": null
    },
    {
      "row_index": 15,
      "col_index": 6,
      "bbox": {
        "x0": 0,
        "y0": 0,
        "x1": 0,
        "y1": 0
      },
      "cell_type": "blank",
      "raw_value": "",
      "normalized_value": "",
      "rowspan": 1,
      "colspan": 1,
      "formula_text": null,
      "units": null
    },
    {
      "row_index": 15,
      "col_index": 7,
      "bbox": {
        "x0": 0,
        "y0": 0,
        "x1": 0,
        "y1": 0
      },
      "cell_type": "number",
      "raw_value": "0.026",
      "normalized_value": 0.026,
      "rowspan": 1,
      "colspan": 1,
      "formula_text": null,
      "units": null
    },
    {
      "row_index": 15,
      "col_index": 8,
      "bbox": {
        "x0": 0,
        "y0": 0,
        "x1": 0,
        "y1": 0
      },
      "cell_type": "blank",
      "raw_value": "",
      "normalized_value": "",
      "rowspan": 1,
      "colspan": 1,
      "formula_text": null,
      "units": null
    },
    {
      "row_index": 15,
      "col_index": 9,
      "bbox": {
        "x0": 0,
        "y0": 0,
        "x1": 0,
        "y1": 0
      },
      "cell_type": "number",
      "raw_value": "0.029",
      "normalized_value": 0.029,
      "rowspan": 1,
      "colspan": 1,
      "formula_text": null,
      "units": null
    },
    {
      "row_index": 15,
      "col_index": 10,
      "bbox": {
        "x0": 0,
        "y0": 0,
        "x1": 0,
        "y1": 0
      },
      "cell_type": "blank",
      "raw_value": "",
      "normalized_value": "",
      "rowspan": 1,
      "colspan": 1,
      "formula_text": null,
      "units": null
    },
    {
      "row_index": 16,
      "col_index": 0,
      "bbox": {
        "x0": 0,
        "y0": 0,
        "x1": 0,
        "y1": 0
      },
      "cell_type": "blank",
      "raw_value": "",
      "normalized_value": "",
      "rowspan": 1,
      "colspan": 1,
      "formula_text": null,
      "units": null
    },
    {
      "row_index": 16,
      "col_index": 1,
      "bbox": {
        "x0": 0,
        "y0": 0,
        "x1": 0,
        "y1": 0
      },
      "cell_type": "text",
      "raw_value": "Median",
      "normalized_value": "Median",
      "rowspan": 1,
      "colspan": 1,
      "formula_text": null,
      "units": null
    },
    {
      "row_index": 16,
      "col_index": 2,
      "bbox": {
        "x0": 0,
        "y0": 0,
        "x1": 0,
        "y1": 0
      },
      "cell_type": "blank",
      "raw_value": "",
      "normalized_value": "",
      "rowspan": 1,
      "colspan": 1,
      "formula_text": null,
      "units": null
    },
    {
      "row_index": 16,
      "col_index": 3,
      "bbox": {
        "x0": 0,
        "y0": 0,
        "x1": 0,
        "y1": 0
      },
      "cell_type": "number",
      "raw_value": "0.939",
      "normalized_value": 0.939,
      "rowspan": 1,
      "colspan": 1,
      "formula_text": null,
      "units": null
    },
    {
      "row_index": 16,
      "col_index": 4,
      "bbox": {
        "x0": 0,
        "y0": 0,
        "x1": 0,
        "y1": 0
      },
      "cell_type": "blank",
      "raw_value": "",
      "normalized_value": "",
      "rowspan": 1,
      "colspan": 1,
      "formula_text": null,
      "units": null
    },
    {
      "row_index": 16,
      "col_index": 5,
      "bbox": {
        "x0": 0,
        "y0": 0,
        "x1": 0,
        "y1": 0
      },
      "cell_type": "number",
      "raw_value": "0.927",
      "normalized_value": 0.927,
      "rowspan": 1,
      "colspan": 1,
      "formula_text": null,
      "units": null
    },
    {
      "row_index": 16,
      "col_index": 6,
      "bbox": {
        "x0": 0,
        "y0": 0,
        "x1": 0,
        "y1": 0
      },
      "cell_type": "blank",
      "raw_value": "",
      "normalized_value": "",
      "rowspan": 1,
      "colspan": 1,
      "formula_text": null,
      "units": null
    },
    {
      "row_index": 16,
      "col_index": 7,
      "bbox": {
        "x0": 0,
        "y0": 0,
        "x1": 0,
        "y1": 0
      },
      "cell_type": "number",
      "raw_value": "0.026",
      "normalized_value": 0.026,
      "rowspan": 1,
      "colspan": 1,
      "formula_text": null,
      "units": null
    },
    {
      "row_index": 16,
      "col_index": 8,
      "bbox": {
        "x0": 0,
        "y0": 0,
        "x1": 0,
        "y1": 0
      },
      "cell_type": "blank",
      "raw_value": "",
      "normalized_value": "",
      "rowspan": 1,
      "colspan": 1,
      "formula_text": null,
      "units": null
    },
    {
      "row_index": 16,
      "col_index": 9,
      "bbox": {
        "x0": 0,
        "y0": 0,
        "x1": 0,
        "y1": 0
      },
      "cell_type": "number",
      "raw_value": "0.024",
      "normalized_value": 0.024,
      "rowspan": 1,
      "colspan": 1,
      "formula_text": null,
      "units": null
    },
    {
      "row_index": 16,
      "col_index": 10,
      "bbox": {
        "x0": 0,
        "y0": 0,
        "x1": 0,
        "y1": 0
      },
      "cell_type": "blank",
      "raw_value": "",
      "normalized_value": "",
      "rowspan": 1,
      "colspan": 1,
      "formula_text": null,
      "units": null
    }
  ],
  "footnotes": [],
  "units": [],
  "formula_cells": [],
  "derived_columns": [],
  "variable_candidates": {},
  "description": "CHAPTER 25 This table contains 17 rows and 11 columns.",
  "table_summary": "CHAPTER 25 This table contains 17 rows and 11 columns.",
  "table_schema_hint": null,
  "linked_concept_ids": [],
  "links": [],
  "source_anchor": {
    "page_number": 906,
    "bbox": {
      "x0": 114.75,
      "y0": 29.079693405555545,
      "x1": 467.7212024999999,
      "y1": 269.84895375
    },
    "extractor": "pdfplumber",
    "confidence": 0.9,
    "metadata": {}
  },
  "confidence": 1.0,
  "heading_path": null,
  "page_span": [
    906,
    906
  ]
}